RTL/gate/gates.v
`timescale 1ns/1ps

module and_gate(a,b,y);
    input wire a,b;
    output wire y;
    assign y = a&b;
endmodule  

module or_gate(a,b,y);
    input wire a,b;
    output wire y;
    assign y = a|b;
endmodule    

module xor_gate(a,b,y);
    input wire a,b;
    output wire y;
    assign y = a^b;
endmodule


module not_gate(a,y);
    input wire a;
    output wire y;
    assign y = ~a;
endmodule 


module nand_gate(a,b,y);
    input wire a,b;
    output wire y;
    assign y = ~(a&b);
endmodule 


module nor_gate(a,b,y);
    input wire a,b;
    output wire y;
    assign y = ~(a|b);
endmodule

RTL/adder/adder.v
module half_adder(a,b,sum,carry);
    input wire a,b;
    output wire sum, carry;

    and_gate AG_01(.a(a), .b(b), .y(carry));
    xor_gate XG_01(.a(a), .b(b), .y(sum));
endmodule

module full_adder(a,b,cin,sum,cout);
    input wire a,b,cin;
    output wire sum,cout;

    wire sum1, carry1, carry2;
    half_adder HA_01(.a(a), .b(b), .sum(sum1), .carry(carry1));
    half_adder HA_02(.a(sum1),.b(cin), .sum(sum), .carry(carry2));

    or_gate OR_01(.a(carry1), .b(carry2), .y(cout));

endmodule

RTL/adder/ripple_carry_adder.v
`timescale 1ns/1ps

module ripple_carry_adder(
    input  wire [7:0] a,
    input  wire [7:0] b,
    input  wire b_invert,
    input  wire cin,
    output wire cout,
    output wire zero_flag,
    output wire negative_flag,
    output wire overflow_flag,
    output wire [7:0] result
);

    wire [7:0] b_modified;

    // When b_invert is high, XOR flips every bit of b (needed for subtraction).
    // When low, b passes straight through untouched.
    
    xor_gate bx0(.a(b[0]), .b(b_invert), .y(b_modified[0]));
    xor_gate bx1(.a(b[1]), .b(b_invert), .y(b_modified[1]));
    xor_gate bx2(.a(b[2]), .b(b_invert), .y(b_modified[2]));
    xor_gate bx3(.a(b[3]), .b(b_invert), .y(b_modified[3]));
    xor_gate bx4(.a(b[4]), .b(b_invert), .y(b_modified[4]));
    xor_gate bx5(.a(b[5]), .b(b_invert), .y(b_modified[5]));
    xor_gate bx6(.a(b[6]), .b(b_invert), .y(b_modified[6]));
    xor_gate bx7(.a(b[7]), .b(b_invert), .y(b_modified[7]));

     wire [6:0] carry;

    // Internal carry ripple chain between stages (bit 0 up to bit 6)
    full_adder fa0(.a(a[0]), .b(b_modified[0]), .cin(cin), .sum(result[0]),
     .cout(carry[0]));
        
    full_adder fa1(.a(a[1]), .b(b_modified[1]), .cin(carry[0]), .sum(result[1]), 
    .cout(carry[1]));
        
    full_adder fa2(.a(a[2]), .b(b_modified[2]), .cin(carry[1]), .sum(result[2]), 
    .cout(carry[2]));
        
    full_adder fa3(.a(a[3]), .b(b_modified[3]), .cin(carry[2]), .sum(result[3]),
    .cout(carry[3]));
    
    full_adder fa4(.a(a[4]), .b(b_modified[4]), .cin(carry[3]), .sum(result[4]),
    .cout(carry[4]));
   
    full_adder fa5(.a(a[5]), .b(b_modified[5]), .cin(carry[4]), .sum(result[5]),
    .cout(carry[5]));  
         
  
    full_adder fa6(.a(a[6]), .b(b_modified[6]), .cin(carry[5]), .sum(result[6]),
    .cout(carry[6]));

    full_adder fa7(.a(a[7]), .b(b_modified[7]), .cin(carry[6]),
    .sum(result[7]), .cout(cout));
    
    // Status flags: 1. Z: high if the result evaluates to all zeros 
                //   2.N: high if the sign bit (MSB) is 1 (two's complement negative)
    assign zero_flag     = (result == 8'b0);
    assign negative_flag = result[7];

    // Signed overflow check: Flags when carry-in to the sign bit (carry[6])
    // doesn't match carry-out (cout)

   xor_gate overflow_xor(.a(carry[6]), .b(cout), .y(overflow_flag));
        
endmodule

RTL/subtractor/subtractor.v
`timescale 1ns/1ps

// 8-bit unsigned subtractor
// Reuses the ripple carry adder configured for two's complement subtraction (A - B)
// Borrow-out (bout) is derived by inverting carry-out:
//   bout = 0 -> A >= B (no borrow needed)
//   bout = 1 -> A < B  (borrow occurred)

module subtractor(
    input  wire [7:0] a,
    input  wire [7:0] b,
    output wire [7:0] result,
    output wire       bout
);

    wire cout;
    wire zero_flag, negative_flag, overflow_flag;

    // Run A + (~B) + 1 through the RCA
    ripple_carry_adder rca(
        .a(a),
        .b(b),
        .b_invert(1'b1),
        .cin(1'b1),
        .result(result),
        .cout(cout),
        .zero_flag(zero_flag),
        .negative_flag(negative_flag),
        .overflow_flag(overflow_flag)
    );

    // Active-high borrow is the complement of carry-out
    assign bout = ~cout;

endmodule

RTL/multiplier/divider.v
`timescale 1ns/1ps

// 8-bit Restoring Division Unit
// Sequential implementation running over 8 compute cycles.
// Computes: dividend / divisor = quotient with remainder.

module divider(
    input  wire        clk,
    input  wire        reset,
    input  wire        start,
    input  wire [7:0]  dividend,
    input  wire [7:0]  divisor,
    output reg  [7:0]  quotient,
    output reg  [7:0]  remainder,
    output reg         done,
    output reg         div_by_zero
);

localparam IDLE    = 2'b00;
localparam COMPUTE = 2'b01;
localparam FINISH  = 2'b10;

reg [1:0] state;
reg [7:0] D;
reg [7:0] V;
reg [7:0] Q;
reg [7:0] R;
reg [2:0] step;

wire [7:0] R_shifted = {R[6:0], D[7]};
wire [7:0] sub_result;
wire       borrow;

subtractor sub_unit(
    .a(R_shifted),
    .b(V),
    .result(sub_result),
    .bout(borrow)
);

always @(posedge clk) begin
    if (reset) begin
        state       <= IDLE;
        quotient    <= 8'd0;
        remainder   <= 8'd0;
        done        <= 1'b0;
        div_by_zero <= 1'b0;
        D           <= 8'd0;
        V           <= 8'd0;
        Q           <= 8'd0;
        R           <= 8'd0;
        step        <= 3'd0;
    end else case (state)
        IDLE: begin
            done <= 1'b0;
            if (start && divisor == 8'b0) begin
                div_by_zero <= 1'b1;
                quotient    <= 8'hFF;
                remainder   <= 8'hFF;
                done        <= 1'b1;
                state       <= IDLE;
            end else if (start) begin
                div_by_zero <= 1'b0;
                D           <= dividend;
                V           <= divisor;
                Q           <= 8'd0;
                R           <= 8'd0;
                step        <= 3'd0;
                state       <= COMPUTE;
            end
        end

        COMPUTE: begin
            R <= (!borrow) ? sub_result : R_shifted;
            Q <= (!borrow) ? {Q[6:0], 1'b1} : {Q[6:0], 1'b0};
            D <= {D[6:0], 1'b0};

            if (step == 3'd7) state <= FINISH;
            else step <= step + 1'b1;
        end

        FINISH: begin
            quotient  <= Q;
            remainder <= R;
            done      <= 1'b1;
            state     <= IDLE;
        end

        default: state <= IDLE;
    endcase
end

endmodule

RTL/testbench/divider_tb.v
`timescale 1ns/1ps

module divider_tb;

    reg        clk, reset, start;
    reg  [7:0] dividend, divisor;
    wire [7:0] quotient, remainder;
    wire       done, div_by_zero;

    divider uut(
        .clk(clk), .reset(reset), .start(start),
        .dividend(dividend), .divisor(divisor),
        .quotient(quotient), .remainder(remainder),
        .done(done), .div_by_zero(div_by_zero)
    );

    initial clk = 0;
    always #5 clk = ~clk;

    task do_divide;
        input [7:0] dd;
        input [7:0] dv;
        input [7:0] exp_q;
        input [7:0] exp_r;
        begin
            @(posedge clk);
            dividend = dd;
            divisor  = dv;
            start    = 1;
            @(posedge clk);
            start = 0;

            // Wait until done goes high
            wait(done == 1'b1);
            @(posedge clk);

            if (div_by_zero) begin
                $display("DIV_BY_ZERO | %0d / %0d", dd, dv);
            end else if (quotient === exp_q && remainder === exp_r) begin
                $display("PASS | %0d / %0d = %0d rem %0d",
                          dd, dv, quotient, remainder);
            end else begin
                $display("FAIL | %0d / %0d = %0d rem %0d (expected q=%0d r=%0d)",
                          dd, dv, quotient, remainder, exp_q, exp_r);
            end

            // Wait for state to return to IDLE
            @(posedge clk);
        end
    endtask

    initial begin
        $dumpfile("divider.vcd");
        $dumpvars(0, divider_tb);

        reset = 1; start = 0;
        repeat(3) @(posedge clk);
        reset = 0;
        @(posedge clk);

        //          dividend  divisor  exp_q  exp_r
        do_divide(  20,       4,       5,     0    );
        do_divide(  22,       4,       5,     2    );
        do_divide(  100,      7,       14,    2    );
        do_divide(  255,      16,      15,    15   );
        do_divide(  1,        1,       1,     0    );
        do_divide(  0,        5,       0,     0    );
        do_divide(  128,      2,       64,    0    );
        do_divide(  200,      13,      15,    5    );
        do_divide(  255,      255,     1,     0    );
        do_divide(  7,        10,      0,     7    ); // divisor > dividend
        do_divide(  10,       0,       0,     0    ); // div by zero

        $display("Divider testbench complete");
        $finish;
    end

endmodule

RTL/vvp_gtk/divider.vcd
$date
	Sun Sep 27 01:55:37 2026
$end
$version
	Icarus Verilog
$end
$timescale
	1ps
$end
$scope module divider_tb $end
$var wire 8 ! remainder [7:0] $end
$var wire 8 " quotient [7:0] $end
$var wire 1 # done $end
$var wire 1 $ div_by_zero $end
$var reg 1 % clk $end
$var reg 8 & dividend [7:0] $end
$var reg 8 ' divisor [7:0] $end
$var reg 1 ( reset $end
$var reg 1 ) start $end
$scope module uut $end
$var wire 1 % clk $end
$var wire 8 * dividend [7:0] $end
$var wire 8 + divisor [7:0] $end
$var wire 1 ( reset $end
$var wire 1 ) start $end
$var wire 8 , sub_result [7:0] $end
$var wire 1 - borrow $end
$var wire 8 . R_shifted [7:0] $end
$var parameter 2 / COMPUTE $end
$var parameter 2 0 FINISH $end
$var parameter 2 1 IDLE $end
$var reg 8 2 D [7:0] $end
$var reg 8 3 Q [7:0] $end
$var reg 8 4 R [7:0] $end
$var reg 8 5 V [7:0] $end
$var reg 1 $ div_by_zero $end
$var reg 1 # done $end
$var reg 8 6 quotient [7:0] $end
$var reg 8 7 remainder [7:0] $end
$var reg 2 8 state [1:0] $end
$var reg 3 9 step [2:0] $end
$scope module sub_unit $end
$var wire 8 : a [7:0] $end
$var wire 8 ; b [7:0] $end
$var wire 1 - bout $end
$var wire 1 < zero_flag $end
$var wire 8 = result [7:0] $end
$var wire 1 > overflow_flag $end
$var wire 1 ? negative_flag $end
$var wire 1 @ cout $end
$scope module rca $end
$var wire 8 A a [7:0] $end
$var wire 8 B b [7:0] $end
$var wire 1 C b_invert $end
$var wire 1 D cin $end
$var wire 1 < zero_flag $end
$var wire 8 E result [7:0] $end
$var wire 1 > overflow_flag $end
$var wire 1 ? negative_flag $end
$var wire 1 @ cout $end
$var wire 7 F carry [6:0] $end
$var wire 8 G b_modified [7:0] $end
$scope module bx0 $end
$var wire 1 H a $end
$var wire 1 C b $end
$var wire 1 I y $end
$upscope $end
$scope module bx1 $end
$var wire 1 J a $end
$var wire 1 C b $end
$var wire 1 K y $end
$upscope $end
$scope module bx2 $end
$var wire 1 L a $end
$var wire 1 C b $end
$var wire 1 M y $end
$upscope $end
$scope module bx3 $end
$var wire 1 N a $end
$var wire 1 C b $end
$var wire 1 O y $end
$upscope $end
$scope module bx4 $end
$var wire 1 P a $end
$var wire 1 C b $end
$var wire 1 Q y $end
$upscope $end
$scope module bx5 $end
$var wire 1 R a $end
$var wire 1 C b $end
$var wire 1 S y $end
$upscope $end
$scope module bx6 $end
$var wire 1 T a $end
$var wire 1 C b $end
$var wire 1 U y $end
$upscope $end
$scope module bx7 $end
$var wire 1 V a $end
$var wire 1 C b $end
$var wire 1 W y $end
$upscope $end
$scope module fa0 $end
$var wire 1 X a $end
$var wire 1 Y b $end
$var wire 1 D cin $end
$var wire 1 Z sum1 $end
$var wire 1 [ sum $end
$var wire 1 \ cout $end
$var wire 1 ] carry2 $end
$var wire 1 ^ carry1 $end
$scope module HA_01 $end
$var wire 1 X a $end
$var wire 1 Y b $end
$var wire 1 Z sum $end
$var wire 1 ^ carry $end
$scope module AG_01 $end
$var wire 1 X a $end
$var wire 1 Y b $end
$var wire 1 ^ y $end
$upscope $end
$scope module XG_01 $end
$var wire 1 X a $end
$var wire 1 Y b $end
$var wire 1 Z y $end
$upscope $end
$upscope $end
$scope module HA_02 $end
$var wire 1 Z a $end
$var wire 1 D b $end
$var wire 1 [ sum $end
$var wire 1 ] carry $end
$scope module AG_01 $end
$var wire 1 Z a $end
$var wire 1 D b $end
$var wire 1 ] y $end
$upscope $end
$scope module XG_01 $end
$var wire 1 Z a $end
$var wire 1 D b $end
$var wire 1 [ y $end
$upscope $end
$upscope $end
$scope module OR_01 $end
$var wire 1 ^ a $end
$var wire 1 ] b $end
$var wire 1 \ y $end
$upscope $end
$upscope $end
$scope module fa1 $end
$var wire 1 _ a $end
$var wire 1 ` b $end
$var wire 1 a cin $end
$var wire 1 b sum1 $end
$var wire 1 c sum $end
$var wire 1 d cout $end
$var wire 1 e carry2 $end
$var wire 1 f carry1 $end
$scope module HA_01 $end
$var wire 1 _ a $end
$var wire 1 ` b $end
$var wire 1 b sum $end
$var wire 1 f carry $end
$scope module AG_01 $end
$var wire 1 _ a $end
$var wire 1 ` b $end
$var wire 1 f y $end
$upscope $end
$scope module XG_01 $end
$var wire 1 _ a $end
$var wire 1 ` b $end
$var wire 1 b y $end
$upscope $end
$upscope $end
$scope module HA_02 $end
$var wire 1 b a $end
$var wire 1 a b $end
$var wire 1 c sum $end
$var wire 1 e carry $end
$scope module AG_01 $end
$var wire 1 b a $end
$var wire 1 a b $end
$var wire 1 e y $end
$upscope $end
$scope module XG_01 $end
$var wire 1 b a $end
$var wire 1 a b $end
$var wire 1 c y $end
$upscope $end
$upscope $end
$scope module OR_01 $end
$var wire 1 f a $end
$var wire 1 e b $end
$var wire 1 d y $end
$upscope $end
$upscope $end
$scope module fa2 $end
$var wire 1 g a $end
$var wire 1 h b $end
$var wire 1 i cin $end
$var wire 1 j sum1 $end
$var wire 1 k sum $end
$var wire 1 l cout $end
$var wire 1 m carry2 $end
$var wire 1 n carry1 $end
$scope module HA_01 $end
$var wire 1 g a $end
$var wire 1 h b $end
$var wire 1 j sum $end
$var wire 1 n carry $end
$scope module AG_01 $end
$var wire 1 g a $end
$var wire 1 h b $end
$var wire 1 n y $end
$upscope $end
$scope module XG_01 $end
$var wire 1 g a $end
$var wire 1 h b $end
$var wire 1 j y $end
$upscope $end
$upscope $end
$scope module HA_02 $end
$var wire 1 j a $end
$var wire 1 i b $end
$var wire 1 k sum $end
$var wire 1 m carry $end
$scope module AG_01 $end
$var wire 1 j a $end
$var wire 1 i b $end
$var wire 1 m y $end
$upscope $end
$scope module XG_01 $end
$var wire 1 j a $end
$var wire 1 i b $end
$var wire 1 k y $end
$upscope $end
$upscope $end
$scope module OR_01 $end
$var wire 1 n a $end
$var wire 1 m b $end
$var wire 1 l y $end
$upscope $end
$upscope $end
$scope module fa3 $end
$var wire 1 o a $end
$var wire 1 p b $end
$var wire 1 q cin $end
$var wire 1 r sum1 $end
$var wire 1 s sum $end
$var wire 1 t cout $end
$var wire 1 u carry2 $end
$var wire 1 v carry1 $end
$scope module HA_01 $end
$var wire 1 o a $end
$var wire 1 p b $end
$var wire 1 r sum $end
$var wire 1 v carry $end
$scope module AG_01 $end
$var wire 1 o a $end
$var wire 1 p b $end
$var wire 1 v y $end
$upscope $end
$scope module XG_01 $end
$var wire 1 o a $end
$var wire 1 p b $end
$var wire 1 r y $end
$upscope $end
$upscope $end
$scope module HA_02 $end
$var wire 1 r a $end
$var wire 1 q b $end
$var wire 1 s sum $end
$var wire 1 u carry $end
$scope module AG_01 $end
$var wire 1 r a $end
$var wire 1 q b $end
$var wire 1 u y $end
$upscope $end
$scope module XG_01 $end
$var wire 1 r a $end
$var wire 1 q b $end
$var wire 1 s y $end
$upscope $end
$upscope $end
$scope module OR_01 $end
$var wire 1 v a $end
$var wire 1 u b $end
$var wire 1 t y $end
$upscope $end
$upscope $end
$scope module fa4 $end
$var wire 1 w a $end
$var wire 1 x b $end
$var wire 1 y cin $end
$var wire 1 z sum1 $end
$var wire 1 { sum $end
$var wire 1 | cout $end
$var wire 1 } carry2 $end
$var wire 1 ~ carry1 $end
$scope module HA_01 $end
$var wire 1 w a $end
$var wire 1 x b $end
$var wire 1 z sum $end
$var wire 1 ~ carry $end
$scope module AG_01 $end
$var wire 1 w a $end
$var wire 1 x b $end
$var wire 1 ~ y $end
$upscope $end
$scope module XG_01 $end
$var wire 1 w a $end
$var wire 1 x b $end
$var wire 1 z y $end
$upscope $end
$upscope $end
$scope module HA_02 $end
$var wire 1 z a $end
$var wire 1 y b $end
$var wire 1 { sum $end
$var wire 1 } carry $end
$scope module AG_01 $end
$var wire 1 z a $end
$var wire 1 y b $end
$var wire 1 } y $end
$upscope $end
$scope module XG_01 $end
$var wire 1 z a $end
$var wire 1 y b $end
$var wire 1 { y $end
$upscope $end
$upscope $end
$scope module OR_01 $end
$var wire 1 ~ a $end
$var wire 1 } b $end
$var wire 1 | y $end
$upscope $end
$upscope $end
$scope module fa5 $end
$var wire 1 !" a $end
$var wire 1 "" b $end
$var wire 1 #" cin $end
$var wire 1 $" sum1 $end
$var wire 1 %" sum $end
$var wire 1 &" cout $end
$var wire 1 '" carry2 $end
$var wire 1 (" carry1 $end
$scope module HA_01 $end
$var wire 1 !" a $end
$var wire 1 "" b $end
$var wire 1 $" sum $end
$var wire 1 (" carry $end
$scope module AG_01 $end
$var wire 1 !" a $end
$var wire 1 "" b $end
$var wire 1 (" y $end
$upscope $end
$scope module XG_01 $end
$var wire 1 !" a $end
$var wire 1 "" b $end
$var wire 1 $" y $end
$upscope $end
$upscope $end
$scope module HA_02 $end
$var wire 1 $" a $end
$var wire 1 #" b $end
$var wire 1 %" sum $end
$var wire 1 '" carry $end
$scope module AG_01 $end
$var wire 1 $" a $end
$var wire 1 #" b $end
$var wire 1 '" y $end
$upscope $end
$scope module XG_01 $end
$var wire 1 $" a $end
$var wire 1 #" b $end
$var wire 1 %" y $end
$upscope $end
$upscope $end
$scope module OR_01 $end
$var wire 1 (" a $end
$var wire 1 '" b $end
$var wire 1 &" y $end
$upscope $end
$upscope $end
$scope module fa6 $end
$var wire 1 )" a $end
$var wire 1 *" b $end
$var wire 1 +" cin $end
$var wire 1 ," sum1 $end
$var wire 1 -" sum $end
$var wire 1 ." cout $end
$var wire 1 /" carry2 $end
$var wire 1 0" carry1 $end
$scope module HA_01 $end
$var wire 1 )" a $end
$var wire 1 *" b $end
$var wire 1 ," sum $end
$var wire 1 0" carry $end
$scope module AG_01 $end
$var wire 1 )" a $end
$var wire 1 *" b $end
$var wire 1 0" y $end
$upscope $end
$scope module XG_01 $end
$var wire 1 )" a $end
$var wire 1 *" b $end
$var wire 1 ," y $end
$upscope $end
$upscope $end
$scope module HA_02 $end
$var wire 1 ," a $end
$var wire 1 +" b $end
$var wire 1 -" sum $end
$var wire 1 /" carry $end
$scope module AG_01 $end
$var wire 1 ," a $end
$var wire 1 +" b $end
$var wire 1 /" y $end
$upscope $end
$scope module XG_01 $end
$var wire 1 ," a $end
$var wire 1 +" b $end
$var wire 1 -" y $end
$upscope $end
$upscope $end
$scope module OR_01 $end
$var wire 1 0" a $end
$var wire 1 /" b $end
$var wire 1 ." y $end
$upscope $end
$upscope $end
$scope module fa7 $end
$var wire 1 1" a $end
$var wire 1 2" b $end
$var wire 1 3" cin $end
$var wire 1 4" sum1 $end
$var wire 1 5" sum $end
$var wire 1 @ cout $end
$var wire 1 6" carry2 $end
$var wire 1 7" carry1 $end
$scope module HA_01 $end
$var wire 1 1" a $end
$var wire 1 2" b $end
$var wire 1 4" sum $end
$var wire 1 7" carry $end
$scope module AG_01 $end
$var wire 1 1" a $end
$var wire 1 2" b $end
$var wire 1 7" y $end
$upscope $end
$scope module XG_01 $end
$var wire 1 1" a $end
$var wire 1 2" b $end
$var wire 1 4" y $end
$upscope $end
$upscope $end
$scope module HA_02 $end
$var wire 1 4" a $end
$var wire 1 3" b $end
$var wire 1 5" sum $end
$var wire 1 6" carry $end
$scope module AG_01 $end
$var wire 1 4" a $end
$var wire 1 3" b $end
$var wire 1 6" y $end
$upscope $end
$scope module XG_01 $end
$var wire 1 4" a $end
$var wire 1 3" b $end
$var wire 1 5" y $end
$upscope $end
$upscope $end
$scope module OR_01 $end
$var wire 1 7" a $end
$var wire 1 6" b $end
$var wire 1 @ y $end
$upscope $end
$upscope $end
$scope module overflow_xor $end
$var wire 1 8" a $end
$var wire 1 @ b $end
$var wire 1 > y $end
$upscope $end
$upscope $end
$upscope $end
$upscope $end
$scope task do_divide $end
$var reg 8 9" dd [7:0] $end
$var reg 8 :" dv [7:0] $end
$var reg 8 ;" exp_q [7:0] $end
$var reg 8 <" exp_r [7:0] $end
$upscope $end
$upscope $end
$enddefinitions $end
$comment Show the parameter values. $end
$dumpall
b0 1
b10 0
b1 /
$end
#0
$dumpvars
bx <"
bx ;"
bx :"
bx 9"
x8"
x7"
x6"
x5"
x4"
x3"
x2"
x1"
x0"
x/"
x."
x-"
x,"
x+"
x*"
x)"
x("
x'"
x&"
x%"
x$"
x#"
x""
x!"
x~
x}
x|
x{
xz
xy
xx
xw
xv
xu
xt
xs
xr
xq
xp
xo
xn
xm
xl
xk
xj
xi
xh
xg
xf
xe
xd
xc
xb
xa
x`
x_
x^
x]
x\
x[
xZ
xY
xX
xW
xV
xU
xT
xS
xR
xQ
xP
xO
xN
xM
xL
xK
xJ
xI
xH
bx G
bx F
bx E
1D
1C
bx B
bx A
x@
x?
x>
bx =
x<
bx ;
bx :
bx 9
bx 8
bx 7
bx 6
bx 5
bx 4
bx 3
bx 2
bx .
x-
bx ,
bx +
bx *
0)
1(
bx '
bx &
0%
x$
x#
bx "
bx !
$end
#5000
0>
0-
1@
0?
16"
1<
05"
13"
18"
1."
1/"
0-"
1+"
1&"
1'"
0%"
1#"
1|
1}
0{
1y
1t
1u
0s
1q
1l
1m
0k
1i
1d
1e
0c
1a
b1111111 F
1\
1]
b0 ,
b0 =
b0 E
0[
1Z
0f
1b
0n
1j
0v
1r
0~
1z
0("
1$"
00"
1,"
07"
14"
1Y
1`
1h
1p
1x
1""
1*"
12"
0^
0_
0g
0o
0w
0!"
0)"
01"
1I
1K
1M
1O
1Q
1S
1U
b11111111 G
1W
0X
0H
0J
0L
0N
0P
0R
0T
0V
b0 .
b0 :
b0 A
b0 9
b0 4
b0 3
b0 5
b0 ;
b0 B
b0 2
0$
0#
b0 !
b0 7
b0 "
b0 6
b0 8
1%
#10000
0%
#15000
1%
#20000
0%
#25000
0(
1%
#30000
0%
#35000
b0 <"
b101 ;"
b100 :"
b10100 9"
1%
#40000
0%
#45000
1-
0@
1?
06"
15"
0>
03"
08"
0."
0/"
1-"
0+"
0&"
0'"
1%"
0#"
0|
0}
1{
0y
0t
0u
1s
0q
b11 F
0l
0m
0<
b11111100 ,
b11111100 =
b11111100 E
1k
0j
0h
b11111011 G
0M
1L
b1 8
b100 5
b100 ;
b100 B
b10100 2
1)
b100 '
b100 +
b10100 &
b10100 *
1%
#50000
0%
#55000
b1 9
b101000 2
0)
1%
#60000
0%
#65000
b10 9
b1010000 2
1%
#70000
0%
#75000
0]
b11111101 ,
b11111101 =
b11111101 E
1[
1^
0Z
1X
b1 .
b1 :
b1 A
b11 9
b10100000 2
1%
#80000
0%
#85000
1]
0[
0e
b11111110 ,
b11111110 =
b11111110 E
1c
0^
1Z
1f
0b
0X
1_
b10 .
b10 :
b10 A
b100 9
b1000000 2
b1 4
1%
#90000
0%
#95000
0-
1@
0?
16"
05"
0>
13"
18"
1."
1/"
0-"
1+"
1&"
1'"
0%"
1#"
1|
1}
0{
1y
1t
1u
0s
1q
b1111111 F
1l
0]
1[
1e
0c
1m
b1 ,
b1 =
b1 E
0k
1^
0Z
0f
1b
1j
1X
0_
1g
b101 .
b101 :
b101 A
b101 9
b10000000 2
b10 4
1%
#100000
0%
#105000
1-
0@
1?
06"
15"
0>
03"
08"
0."
0/"
1-"
0+"
0&"
0'"
1%"
0#"
0|
0}
1{
0y
0t
0u
1s
0q
b11 F
0l
1]
0[
0e
1c
0m
b11111110 ,
b11111110 =
b11111110 E
1k
0^
1Z
1f
0b
0j
0X
1_
0g
b10 .
b10 :
b10 A
b110 9
b0 2
b1 3
b1 4
1%
#110000
0%
#115000
0-
1@
0?
16"
1<
05"
0>
13"
18"
1."
1/"
0-"
1+"
1&"
1'"
0%"
1#"
1|
1}
0{
1y
1t
1u
0s
1q
b1111111 F
1l
1e
0c
1m
b0 ,
b0 =
b0 E
0k
0f
1b
1j
0_
1g
b100 .
b100 :
b100 A
b111 9
b10 3
b10 4
1%
#120000
0%
#125000
1-
0@
1?
06"
15"
0>
03"
08"
0."
0/"
1-"
0+"
0&"
0'"
1%"
0#"
0|
0}
1{
0y
0t
0u
1s
0q
b11 F
0l
0m
0<
b11111100 ,
b11111100 =
b11111100 E
1k
0j
0g
b0 .
b0 :
b0 A
b10 8
b101 3
b0 4
1%
#130000
0%
#135000
b0 8
1#
b101 "
b101 6
1%
#140000
0%
#145000
0#
1%
#150000
0%
#155000
b10 <"
b10110 9"
1%
#160000
0%
#165000
b1 8
b0 9
b0 3
b10110 2
1)
b10110 &
b10110 *
1%
#170000
0%
#175000
b1 9
b101100 2
0)
1%
#180000
0%
#185000
b10 9
b1011000 2
1%
#190000
0%
#195000
0]
b11111101 ,
b11111101 =
b11111101 E
1[
1^
0Z
1X
b1 .
b1 :
b1 A
b11 9
b10110000 2
1%
#200000
0%
#205000
1]
0[
0e
b11111110 ,
b11111110 =
b11111110 E
1c
0^
1Z
1f
0b
0X
1_
b10 .
b10 :
b10 A
b100 9
b1100000 2
b1 4
1%
#210000
0%
#215000
0-
1@
0?
16"
05"
0>
13"
18"
1."
1/"
0-"
1+"
1&"
1'"
0%"
1#"
1|
1}
0{
1y
1t
1u
0s
1q
b1111111 F
1l
0]
1[
1e
0c
1m
b1 ,
b1 =
b1 E
0k
1^
0Z
0f
1b
1j
1X
0_
1g
b101 .
b101 :
b101 A
b101 9
b11000000 2
b10 4
1%
#220000
0%
#225000
1-
0@
1?
06"
15"
0>
03"
08"
0."
0/"
1-"
0+"
0&"
0'"
1%"
0#"
0|
0}
1{
0y
0t
0u
1s
0q
b11 F
0l
0e
1c
0m
b11111111 ,
b11111111 =
b11111111 E
1k
1f
0b
0j
1_
0g
b11 .
b11 :
b11 A
b110 9
b10000000 2
b1 3
b1 4
1%
#230000
0%
#235000
0-
1@
0?
16"
05"
0>
13"
18"
1."
1/"
0-"
1+"
1&"
1'"
0%"
1#"
1|
1}
0{
1y
1t
1u
0s
1q
b1111111 F
1l
1]
0[
1m
b10 ,
b10 =
b10 E
0k
0^
1Z
1j
0X
1g
b110 .
b110 :
b110 A
b111 9
b0 2
b10 3
b11 4
1%
#240000
0%
#245000
1e
1<
b0 ,
b0 =
b0 E
0c
0f
1b
0_
b100 .
b100 :
b100 A
b10 8
b101 3
b10 4
1%
#250000
0%
#255000
b0 8
1#
b10 !
b10 7
1%
#260000
0%
#265000
0#
1%
#270000
0%
#275000
b1110 ;"
b111 :"
b1100100 9"
1%
#280000
0%
#285000
1-
0@
1?
06"
15"
0>
03"
08"
0."
0/"
1-"
0+"
0&"
0'"
1%"
0#"
0|
0}
1{
0y
0t
0u
1s
0a
0i
0q
0\
0d
b0 F
0l
0]
1[
0e
0c
0m
0<
b11111001 ,
b11111001 =
b11111001 E
0k
0Z
0b
0j
0Y
0`
0g
0I
b11111000 G
0K
b0 .
b0 :
b0 A
1H
1J
b1 8
b0 9
b0 4
b0 3
b111 5
b111 ;
b111 B
b1100100 2
1)
b111 '
b111 +
b1100100 &
b1100100 *
1%
#290000
0%
#295000
1c
1a
b1 F
1\
1]
b11111010 ,
b11111010 =
b11111010 E
0[
1Z
1X
b1 .
b1 :
b1 A
b1 9
b11001000 2
0)
1%
#300000
0%
#305000
1k
1i
b11 F
1d
1e
b11111100 ,
b11111100 =
b11111100 E
0c
1b
1_
b11 .
b11 :
b11 A
b10 9
b10010000 2
b1 4
1%
#310000
0%
#315000
1-
0@
1?
06"
15"
0>
03"
08"
0."
0/"
1-"
0+"
0&"
0'"
1%"
0#"
0|
0}
1{
0i
0y
0d
0t
0e
1c
0u
1s
0a
0q
0\
b0 F
0l
0]
1[
0m
b11111111 ,
b11111111 =
b11111111 E
1k
0Z
1j
0X
1g
b110 .
b110 :
b110 A
b11 9
b100000 2
b11 4
1%
#320000
0%
#325000
0-
1@
0?
16"
05"
0>
13"
18"
1."
1/"
0-"
1+"
1&"
1'"
0%"
1#"
1|
1}
0{
1y
0c
b1111000 F
1t
b101 ,
b101 =
b101 E
0s
0b
1v
0r
0_
1o
b1100 .
b1100 :
b1100 A
b100 9
b1000000 2
b110 4
1%
#330000
0%
#335000
1i
1d
1e
0<
1a
b1111011 F
1\
1]
0[
0c
b100 ,
b100 =
b100 E
1k
1Z
1b
0j
1X
1_
0g
b1011 .
b1011 :
b1011 A
b101 9
b10000000 2
b1 3
b101 4
1%
#340000
0%
#345000
0k
0a
0i
0\
b1111000 F
0d
0]
1[
0e
b1 ,
b1 =
b1 E
0c
0Z
0b
0X
0_
b1000 .
b1000 :
b1000 A
b110 9
b0 2
b11 3
b100 4
1%
#350000
0%
#355000
1-
0@
1?
06"
15"
0>
03"
08"
0."
0/"
1-"
0+"
0&"
0'"
1%"
0#"
0|
0}
1{
0y
1c
b0 F
0t
b11111011 ,
b11111011 =
b11111011 E
1s
1b
0v
1r
1_
0o
b10 .
b10 :
b10 A
b111 9
b111 3
b1 4
1%
#360000
0%
#365000
0c
b11111101 ,
b11111101 =
b11111101 E
1k
0b
1j
0_
1g
b100 .
b100 :
b100 A
b10 8
b1110 3
b10 4
1%
#370000
0%
#375000
b0 8
1#
b1110 "
b1110 6
1%
#380000
0%
#385000
0#
1%
#390000
0%
#395000
b1111 <"
b1111 ;"
b10000 :"
b11111111 9"
1%
#400000
0%
