RTL/gate/gates.v
`timescale 1ns/1ps

module and_gate(a,b,y);
    input wire a,b;
    output wire y;
    assign y = a&b;
endmodule  

module or_gate(a,b,y);
    input wire a,b;
    output wire y;
    assign y = a|b;
endmodule    

module xor_gate(a,b,y);
    input wire a,b;
    output wire y;
    assign y = a^b;
endmodule


module not_gate(a,y);
    input wire a;
    output wire y;
    assign y = ~a;
endmodule 


module nand_gate(a,b,y);
    input wire a,b;
    output wire y;
    assign y = ~(a&b);
endmodule 


module nor_gate(a,b,y);
    input wire a,b;
    output wire y;
    assign y = ~(a|b);
endmodule

RTL/adder/adder.v
module half_adder(a,b,sum,carry);
    input wire a,b;
    output wire sum, carry;

    and_gate AG_01(.a(a), .b(b), .y(carry));
    xor_gate XG_01(.a(a), .b(b), .y(sum));
endmodule

module full_adder(a,b,cin,sum,cout);
    input wire a,b,cin;
    output wire sum,cout;

    wire sum1, carry1, carry2;
    half_adder HA_01(.a(a), .b(b), .sum(sum1), .carry(carry1));
    half_adder HA_02(.a(sum1),.b(cin), .sum(sum), .carry(carry2));

    or_gate OR_01(.a(carry1), .b(carry2), .y(cout));

endmodule

RTL/testbench/full_adder_tb.v
`timescale 1ns / 1ps

module full_adder_tb;

    // Inputs to UUT (driven as reg)
    reg a;
    reg b;
    reg cin;

    // Outputs from UUT (monitored as wire)
    wire sum;
    wire cout;

    // Instantiate your full_adder
    full_adder uut (
        .a(a),
        .b(b),
        .cin(cin),
        .sum(sum),
        .cout(cout)
    );

    initial begin
        // Generate waveform file for GTKWave viewing
        $dumpfile("full_adder.vcd");
        $dumpvars(0, full_adder_tb);

        // Display results whenever any signal changes
        $monitor("Time = %0t | a = %b, b = %b, cin = %b | sum = %b, cout = %b", 
                 $time, a, b, cin, sum, cout);

        // Apply all 8 input combinations with a 10ns delay between each
        a = 0; b = 0; cin = 0; #10;
        a = 0; b = 0; cin = 1; #10;
        a = 0; b = 1; cin = 0; #10;
        a = 0; b = 1; cin = 1; #10;
        a = 1; b = 0; cin = 0; #10;
        a = 1; b = 0; cin = 1; #10;
        a = 1; b = 1; cin = 0; #10;
        a = 1; b = 1; cin = 1; #10;

        $finish;
    end

endmodule

RTL/vvp_gtk/full_adder.vcd
$date
	Sat Sep 26 16:50:14 2026
$end
$version
	Icarus Verilog
$end
$timescale
	1ps
$end
$scope module full_adder_tb $end
$var wire 1 ! sum $end
$var wire 1 " cout $end
$var reg 1 # a $end
$var reg 1 $ b $end
$var reg 1 % cin $end
$scope module uut $end
$var wire 1 # a $end
$var wire 1 $ b $end
$var wire 1 % cin $end
$var wire 1 & sum1 $end
$var wire 1 ! sum $end
$var wire 1 " cout $end
$var wire 1 ' carry2 $end
$var wire 1 ( carry1 $end
$scope module HA_01 $end
$var wire 1 # a $end
$var wire 1 $ b $end
$var wire 1 & sum $end
$var wire 1 ( carry $end
$scope module AG_01 $end
$var wire 1 # a $end
$var wire 1 $ b $end
$var wire 1 ( y $end
$upscope $end
$scope module XG_01 $end
$var wire 1 # a $end
$var wire 1 $ b $end
$var wire 1 & y $end
$upscope $end
$upscope $end
$scope module HA_02 $end
$var wire 1 & a $end
$var wire 1 % b $end
$var wire 1 ! sum $end
$var wire 1 ' carry $end
$scope module AG_01 $end
$var wire 1 & a $end
$var wire 1 % b $end
$var wire 1 ' y $end
$upscope $end
$scope module XG_01 $end
$var wire 1 & a $end
$var wire 1 % b $end
$var wire 1 ! y $end
$upscope $end
$upscope $end
$scope module OR_01 $end
$var wire 1 ( a $end
$var wire 1 ' b $end
$var wire 1 " y $end
$upscope $end
$upscope $end
$upscope $end
$enddefinitions $end
$comment Show the parameter values. $end
$dumpall
$end
#0
$dumpvars
0(
0'
0&
0%
0$
0#
0"
0!
$end
#10000
1!
1%
#20000
1&
0%
1$
#30000
1"
1'
0!
1%
#40000
0"
0'
1!
0%
0$
1#
#50000
1"
1'
0!
1%
#60000
0'
1(
0&
0%
1$
#70000
1!
1%
