RTL/gate/gates.v
`timescale 1ns/1ps

module and_gate(a,b,y);
    input wire a,b;
    output wire y;
    assign y = a&b;
endmodule  

module or_gate(a,b,y);
    input wire a,b;
    output wire y;
    assign y = a|b;
endmodule    

module xor_gate(a,b,y);
    input wire a,b;
    output wire y;
    assign y = a^b;
endmodule


module not_gate(a,y);
    input wire a;
    output wire y;
    assign y = ~a;
endmodule 


module nand_gate(a,b,y);
    input wire a,b;
    output wire y;
    assign y = ~(a&b);
endmodule 


module nor_gate(a,b,y);
    input wire a,b;
    output wire y;
    assign y = ~(a|b);
endmodule

RTL/logic_unit/logic.v
`timescale 1ns/1ps

module logic_unit(
    input  wire [7:0] a,
    input  wire [7:0] b,
    input  wire [2:0] op,
    output reg  [7:0] result
);
    // op=00 → AND
    // op=01 → OR
    // op=10 → XOR
    // op=11 → NOT a

    wire [7:0] and_result;
    wire [7:0] or_result;
    wire [7:0] xor_result;
    wire [7:0] not_result;

    // Instantiate 8 gates for each operation
    and_gate a0(.a(a[0]),.b(b[0]),.y(and_result[0]));
    and_gate a1(.a(a[1]),.b(b[1]),.y(and_result[1]));
    and_gate a2(.a(a[2]),.b(b[2]),.y(and_result[2]));
    and_gate a3(.a(a[3]),.b(b[3]),.y(and_result[3]));
    and_gate a4(.a(a[4]),.b(b[4]),.y(and_result[4]));
    and_gate a5(.a(a[5]),.b(b[5]),.y(and_result[5]));
    and_gate a6(.a(a[6]),.b(b[6]),.y(and_result[6]));
    and_gate a7(.a(a[7]),.b(b[7]),.y(and_result[7]));

    or_gate  o0(.a(a[0]),.b(b[0]),.y(or_result[0]));
    or_gate  o1(.a(a[1]),.b(b[1]),.y(or_result[1]));
    or_gate  o2(.a(a[2]),.b(b[2]),.y(or_result[2]));
    or_gate  o3(.a(a[3]),.b(b[3]),.y(or_result[3]));
    or_gate  o4(.a(a[4]),.b(b[4]),.y(or_result[4]));
    or_gate  o5(.a(a[5]),.b(b[5]),.y(or_result[5]));
    or_gate  o6(.a(a[6]),.b(b[6]),.y(or_result[6]));
    or_gate  o7(.a(a[7]),.b(b[7]),.y(or_result[7]));

    xor_gate x0(.a(a[0]),.b(b[0]),.y(xor_result[0]));
    xor_gate x1(.a(a[1]),.b(b[1]),.y(xor_result[1]));
    xor_gate x2(.a(a[2]),.b(b[2]),.y(xor_result[2]));
    xor_gate x3(.a(a[3]),.b(b[3]),.y(xor_result[3]));
    xor_gate x4(.a(a[4]),.b(b[4]),.y(xor_result[4]));
    xor_gate x5(.a(a[5]),.b(b[5]),.y(xor_result[5]));
    xor_gate x6(.a(a[6]),.b(b[6]),.y(xor_result[6]));
    xor_gate x7(.a(a[7]),.b(b[7]),.y(xor_result[7]));

    not_gate n0(.a(a[0]),.y(not_result[0]));
    not_gate n1(.a(a[1]),.y(not_result[1]));
    not_gate n2(.a(a[2]),.y(not_result[2]));
    not_gate n3(.a(a[3]),.y(not_result[3]));
    not_gate n4(.a(a[4]),.y(not_result[4]));
    not_gate n5(.a(a[5]),.y(not_result[5]));
    not_gate n6(.a(a[6]),.y(not_result[6]));
    not_gate n7(.a(a[7]),.y(not_result[7]));

        // NAND: 8 bits
    wire [7:0] nand_result;
    nand_gate na0(.a(a[0]),.b(b[0]),.y(nand_result[0]));
    nand_gate na1(.a(a[1]),.b(b[1]),.y(nand_result[1]));
    nand_gate na2(.a(a[2]),.b(b[2]),.y(nand_result[2]));
    nand_gate na3(.a(a[3]),.b(b[3]),.y(nand_result[3]));
    nand_gate na4(.a(a[4]),.b(b[4]),.y(nand_result[4]));
    nand_gate na5(.a(a[5]),.b(b[5]),.y(nand_result[5]));
    nand_gate na6(.a(a[6]),.b(b[6]),.y(nand_result[6]));
    nand_gate na7(.a(a[7]),.b(b[7]),.y(nand_result[7]));

    // NOR: 8 bits
    wire [7:0] nor_result;
    nor_gate nr0(.a(a[0]),.b(b[0]),.y(nor_result[0]));
    nor_gate nr1(.a(a[1]),.b(b[1]),.y(nor_result[1]));
    nor_gate nr2(.a(a[2]),.b(b[2]),.y(nor_result[2]));
    nor_gate nr3(.a(a[3]),.b(b[3]),.y(nor_result[3]));
    nor_gate nr4(.a(a[4]),.b(b[4]),.y(nor_result[4]));
    nor_gate nr5(.a(a[5]),.b(b[5]),.y(nor_result[5]));
    nor_gate nr6(.a(a[6]),.b(b[6]),.y(nor_result[6]));
    nor_gate nr7(.a(a[7]),.b(b[7]),.y(nor_result[7]));

    always @(*) begin
        case (op)
            3'b000: result = and_result;
            3'b001: result = or_result;
            3'b010: result = xor_result;
            3'b011: result = not_result;
            3'b100: result = nand_result;
            3'b101: result = nor_result;
            default: result = 8'b0;
        endcase
    end

endmodule

RTL/testbench/logic_unit_tb.v
`timescale 1ns/1ps

module logic_unit_tb;

    reg  [7:0] a, b;
    reg  [2:0] op;
    wire [7:0] result;

    logic_unit uut(
        .a(a),
        .b(b),
        .op(op),
        .result(result)
    );

    task check;
        input [7:0]      expected;
        input [7:0]      in_a, in_b;
        input [2:0]      in_op;
        input [8*25-1:0] label;
        begin
            #10;
            if (result === expected)
                $display("PASS | %-25s | result=%08b (%0d)",
                          label, result, result);
            else
                $display("FAIL | %-25s | got=%08b expected=%08b",
                          label, result, expected);
        end
    endtask

    initial begin
        $dumpfile("logic_unit.vcd");
        $dumpvars(0, logic_unit_tb);

        // ── AND (op=00) ───────────────────────────────────────
        a=8'hFF; b=8'h0F; op=3'b000;
        check(8'h0F, a, b, op, "AND FF & 0F");

        a=8'hAA; b=8'h55; op=3'b000;
        check(8'h00, a, b, op, "AND AA & 55 zero");

        a=8'hFF; b=8'hFF; op=3'b000;
        check(8'hFF, a, b, op, "AND FF & FF");

        a=8'h00; b=8'hFF; op=3'b000;
        check(8'h00, a, b, op, "AND 00 & FF zero");

        a=8'b10101010; b=8'b11001100; op=3'b000;
        check(8'b10001000, a, b, op, "AND AA & CC");

        // ── OR (op=01) ────────────────────────────────────────
        a=8'hF0; b=8'h0F; op=3'b001;
        check(8'hFF, a, b, op, "OR F0 | 0F");

        a=8'h00; b=8'h00; op=3'b001;
        check(8'h00, a, b, op, "OR 00 | 00 zero");

        a=8'hAA; b=8'h55; op=3'b001;
        check(8'hFF, a, b, op, "OR AA | 55");

        a=8'hFF; b=8'h00; op=3'b001;
        check(8'hFF, a, b, op, "OR FF | 00");

        a=8'b10101010; b=8'b01010101; op=3'b001;
        check(8'hFF, a, b, op, "OR AA | 55 = FF");

        // ── XOR (op=10) ───────────────────────────────────────
        a=8'hFF; b=8'hFF; op=3'b010;
        check(8'h00, a, b, op, "XOR FF ^ FF zero");

        a=8'hAA; b=8'h55; op=3'b010;
        check(8'hFF, a, b, op, "XOR AA ^ 55");

        a=8'h00; b=8'hFF; op=3'b010;
        check(8'hFF, a, b, op, "XOR 00 ^ FF");

        a=8'hFF; b=8'h00; op=3'b010;
        check(8'hFF, a, b, op, "XOR FF ^ 00");

        a=8'b10101010; b=8'b10101010; op=3'b010;
        check(8'h00, a, b, op, "XOR same inputs zero");

        // ── NOT (op=11) ───────────────────────────────────────
        // NOT only uses input a, b is ignored
        a=8'h00; b=8'h00; op=3'b011;
        check(8'hFF, a, b, op, "NOT 00 = FF");

        a=8'hFF; b=8'h00; op=3'b011;
        check(8'h00, a, b, op, "NOT FF = 00");

        a=8'b10101010; b=8'h00; op=3'b011;
        check(8'b01010101, a, b, op, "NOT AA = 55");

        a=8'b01010101; b=8'h00; op=3'b011;
        check(8'b10101010, a, b, op, "NOT 55 = AA");

        a=8'b11110000; b=8'h00; op=3'b011;
        check(8'b00001111, a, b, op, "NOT F0 = 0F");

                // ── NAND (op=100) ─────────────────────────────────────
        a=8'hFF; b=8'hFF; op=3'b100;
        check(8'h00, a, b, op, "NAND FF & FF = 00");

        a=8'hFF; b=8'h0F; op=3'b100;
        check(8'hF0, a, b, op, "NAND FF & 0F = F0");

        a=8'h00; b=8'hFF; op=3'b100;
        check(8'hFF, a, b, op, "NAND 00 & FF = FF");

        a=8'hAA; b=8'h55; op=3'b100;
        check(8'hFF, a, b, op, "NAND AA & 55 = FF");

        a=8'b10101010; b=8'b11001100; op=3'b100;
        check(8'b01110111, a, b, op, "NAND AA & CC");

        // ── NOR (op=101) ──────────────────────────────────────
        a=8'hFF; b=8'h00; op=3'b101;
        check(8'h00, a, b, op, "NOR FF | 00 = 00");

        a=8'h00; b=8'h00; op=3'b101;
        check(8'hFF, a, b, op, "NOR 00 | 00 = FF");

        a=8'hF0; b=8'h0F; op=3'b101;
        check(8'h00, a, b, op, "NOR F0 | 0F = 00");

        a=8'hAA; b=8'h55; op=3'b101;
        check(8'h00, a, b, op, "NOR AA | 55 = 00");

        a=8'b10100000; b=8'b00001010; op=3'b101;
        check(8'b01010101, a, b, op, "NOR A0 | 0A");
        
        $display("Logic unit testbench complete");
        $finish;
    end

endmodule

RTL/vvp_gtk/logic_unit.vcd
$date
	Sun Sep 27 12:50:10 2026
$end
$version
	Icarus Verilog
$end
$timescale
	1ps
$end
$scope module logic_unit_tb $end
$var wire 8 ! result [7:0] $end
$var reg 8 " a [7:0] $end
$var reg 8 # b [7:0] $end
$var reg 3 $ op [2:0] $end
$scope module uut $end
$var wire 8 % a [7:0] $end
$var wire 8 & b [7:0] $end
$var wire 3 ' op [2:0] $end
$var wire 8 ( xor_result [7:0] $end
$var wire 8 ) or_result [7:0] $end
$var wire 8 * not_result [7:0] $end
$var wire 8 + nor_result [7:0] $end
$var wire 8 , nand_result [7:0] $end
$var wire 8 - and_result [7:0] $end
$var reg 8 . result [7:0] $end
$scope module a0 $end
$var wire 1 / a $end
$var wire 1 0 b $end
$var wire 1 1 y $end
$upscope $end
$scope module a1 $end
$var wire 1 2 a $end
$var wire 1 3 b $end
$var wire 1 4 y $end
$upscope $end
$scope module a2 $end
$var wire 1 5 a $end
$var wire 1 6 b $end
$var wire 1 7 y $end
$upscope $end
$scope module a3 $end
$var wire 1 8 a $end
$var wire 1 9 b $end
$var wire 1 : y $end
$upscope $end
$scope module a4 $end
$var wire 1 ; a $end
$var wire 1 < b $end
$var wire 1 = y $end
$upscope $end
$scope module a5 $end
$var wire 1 > a $end
$var wire 1 ? b $end
$var wire 1 @ y $end
$upscope $end
$scope module a6 $end
$var wire 1 A a $end
$var wire 1 B b $end
$var wire 1 C y $end
$upscope $end
$scope module a7 $end
$var wire 1 D a $end
$var wire 1 E b $end
$var wire 1 F y $end
$upscope $end
$scope module n0 $end
$var wire 1 G a $end
$var wire 1 H y $end
$upscope $end
$scope module n1 $end
$var wire 1 I a $end
$var wire 1 J y $end
$upscope $end
$scope module n2 $end
$var wire 1 K a $end
$var wire 1 L y $end
$upscope $end
$scope module n3 $end
$var wire 1 M a $end
$var wire 1 N y $end
$upscope $end
$scope module n4 $end
$var wire 1 O a $end
$var wire 1 P y $end
$upscope $end
$scope module n5 $end
$var wire 1 Q a $end
$var wire 1 R y $end
$upscope $end
$scope module n6 $end
$var wire 1 S a $end
$var wire 1 T y $end
$upscope $end
$scope module n7 $end
$var wire 1 U a $end
$var wire 1 V y $end
$upscope $end
$scope module na0 $end
$var wire 1 W a $end
$var wire 1 X b $end
$var wire 1 Y y $end
$upscope $end
$scope module na1 $end
$var wire 1 Z a $end
$var wire 1 [ b $end
$var wire 1 \ y $end
$upscope $end
$scope module na2 $end
$var wire 1 ] a $end
$var wire 1 ^ b $end
$var wire 1 _ y $end
$upscope $end
$scope module na3 $end
$var wire 1 ` a $end
$var wire 1 a b $end
$var wire 1 b y $end
$upscope $end
$scope module na4 $end
$var wire 1 c a $end
$var wire 1 d b $end
$var wire 1 e y $end
$upscope $end
$scope module na5 $end
$var wire 1 f a $end
$var wire 1 g b $end
$var wire 1 h y $end
$upscope $end
$scope module na6 $end
$var wire 1 i a $end
$var wire 1 j b $end
$var wire 1 k y $end
$upscope $end
$scope module na7 $end
$var wire 1 l a $end
$var wire 1 m b $end
$var wire 1 n y $end
$upscope $end
$scope module nr0 $end
$var wire 1 o a $end
$var wire 1 p b $end
$var wire 1 q y $end
$upscope $end
$scope module nr1 $end
$var wire 1 r a $end
$var wire 1 s b $end
$var wire 1 t y $end
$upscope $end
$scope module nr2 $end
$var wire 1 u a $end
$var wire 1 v b $end
$var wire 1 w y $end
$upscope $end
$scope module nr3 $end
$var wire 1 x a $end
$var wire 1 y b $end
$var wire 1 z y $end
$upscope $end
$scope module nr4 $end
$var wire 1 { a $end
$var wire 1 | b $end
$var wire 1 } y $end
$upscope $end
$scope module nr5 $end
$var wire 1 ~ a $end
$var wire 1 !" b $end
$var wire 1 "" y $end
$upscope $end
$scope module nr6 $end
$var wire 1 #" a $end
$var wire 1 $" b $end
$var wire 1 %" y $end
$upscope $end
$scope module nr7 $end
$var wire 1 &" a $end
$var wire 1 '" b $end
$var wire 1 (" y $end
$upscope $end
$scope module o0 $end
$var wire 1 )" a $end
$var wire 1 *" b $end
$var wire 1 +" y $end
$upscope $end
$scope module o1 $end
$var wire 1 ," a $end
$var wire 1 -" b $end
$var wire 1 ." y $end
$upscope $end
$scope module o2 $end
$var wire 1 /" a $end
$var wire 1 0" b $end
$var wire 1 1" y $end
$upscope $end
$scope module o3 $end
$var wire 1 2" a $end
$var wire 1 3" b $end
$var wire 1 4" y $end
$upscope $end
$scope module o4 $end
$var wire 1 5" a $end
$var wire 1 6" b $end
$var wire 1 7" y $end
$upscope $end
$scope module o5 $end
$var wire 1 8" a $end
$var wire 1 9" b $end
$var wire 1 :" y $end
$upscope $end
$scope module o6 $end
$var wire 1 ;" a $end
$var wire 1 <" b $end
$var wire 1 =" y $end
$upscope $end
$scope module o7 $end
$var wire 1 >" a $end
$var wire 1 ?" b $end
$var wire 1 @" y $end
$upscope $end
$scope module x0 $end
$var wire 1 A" a $end
$var wire 1 B" b $end
$var wire 1 C" y $end
$upscope $end
$scope module x1 $end
$var wire 1 D" a $end
$var wire 1 E" b $end
$var wire 1 F" y $end
$upscope $end
$scope module x2 $end
$var wire 1 G" a $end
$var wire 1 H" b $end
$var wire 1 I" y $end
$upscope $end
$scope module x3 $end
$var wire 1 J" a $end
$var wire 1 K" b $end
$var wire 1 L" y $end
$upscope $end
$scope module x4 $end
$var wire 1 M" a $end
$var wire 1 N" b $end
$var wire 1 O" y $end
$upscope $end
$scope module x5 $end
$var wire 1 P" a $end
$var wire 1 Q" b $end
$var wire 1 R" y $end
$upscope $end
$scope module x6 $end
$var wire 1 S" a $end
$var wire 1 T" b $end
$var wire 1 U" y $end
$upscope $end
$scope module x7 $end
$var wire 1 V" a $end
$var wire 1 W" b $end
$var wire 1 X" y $end
$upscope $end
$upscope $end
$scope task check $end
$var reg 8 Y" expected [7:0] $end
$var reg 8 Z" in_a [7:0] $end
$var reg 8 [" in_b [7:0] $end
$var reg 3 \" in_op [2:0] $end
$var reg 200 ]" label [199:0] $end
$upscope $end
$upscope $end
$enddefinitions $end
$comment Show the parameter values. $end
$dumpall
$end
#0
$dumpvars
b100000101001110010001000010000001000110010001100010000000100110001000000011000001000110 ]"
b0 \"
b1111 ["
b11111111 Z"
b1111 Y"
1X"
0W"
1V"
1U"
0T"
1S"
1R"
0Q"
1P"
1O"
0N"
1M"
0L"
1K"
1J"
0I"
1H"
1G"
0F"
1E"
1D"
0C"
1B"
1A"
1@"
0?"
1>"
1="
0<"
1;"
1:"
09"
18"
17"
06"
15"
14"
13"
12"
11"
10"
1/"
1."
1-"
1,"
1+"
1*"
1)"
0("
0'"
1&"
0%"
0$"
1#"
0""
0!"
1~
0}
0|
1{
0z
1y
1x
0w
1v
1u
0t
1s
1r
0q
1p
1o
1n
0m
1l
1k
0j
1i
1h
0g
1f
1e
0d
1c
0b
1a
1`
0_
1^
1]
0\
1[
1Z
0Y
1X
1W
0V
1U
0T
1S
0R
1Q
0P
1O
0N
1M
0L
1K
0J
1I
0H
1G
0F
0E
1D
0C
0B
1A
0@
0?
1>
0=
0<
1;
1:
19
18
17
16
15
14
13
12
11
10
1/
b1111 .
b1111 -
b11110000 ,
b0 +
b0 *
b11111111 )
b11110000 (
b0 '
b1111 &
b11111111 %
b0 $
b1111 #
b11111111 "
b1111 !
$end
#10000
1\
1b
b0 !
b0 .
1Y
b11111111 ,
1_
04
0:
1F"
1L"
01
b0 -
07
1C"
b11111111 (
1I"
1H
1L
1P
b1010101 *
1T
03
09
1<
1B
0-"
03"
16"
1<"
0E"
0K"
1N"
1T"
0[
0a
1d
1j
0s
0y
1|
1$"
0/
05
0;
0A
0)"
0/"
05"
0;"
0A"
0G"
0M"
0S"
0G
0K
0O
0S
0W
0]
0c
0i
0o
0u
0{
0#"
b1000001010011100100010000100000010000010100000100100000001001100010000000110101001101010010000001111010011001010111001001101111 ]"
b1010101 ["
b10101010 Z"
b0 Y"
b1010101 #
b1010101 &
b10101010 "
b10101010 %
#20000
0\
0b
0h
0n
b11111111 !
b11111111 .
0Y
0_
0e
b0 ,
0k
14
1:
1@
1F
0F"
0L"
0R"
0X"
11
17
1=
b11111111 -
1C
0C"
0I"
0O"
b0 (
0U"
0H
0L
0P
b0 *
0T
13
19
1?
1E
1-"
13"
19"
1?"
1E"
1K"
1Q"
1W"
1[
1a
1g
1m
1s
1y
1!"
1'"
1/
15
1;
1A
1)"
1/"
15"
1;"
1A"
1G"
1M"
1S"
1G
1K
1O
1S
1W
1]
1c
1i
1o
1u
1{
1#"
b100000101001110010001000010000001000110010001100010000000100110001000000100011001000110 ]"
b11111111 ["
b11111111 Z"
b11111111 Y"
b11111111 #
b11111111 &
b11111111 "
b11111111 %
#30000
b0 !
b0 .
1Y
1\
1_
1b
1e
1h
1k
b11111111 ,
1n
01
04
07
0:
0=
0@
0C
b0 -
0F
1C"
1F"
1I"
1L"
1O"
1R"
1U"
b11111111 (
1X"
1H
1J
1L
1N
1P
1R
1T
b11111111 *
1V
0/
02
05
08
0;
0>
0A
0D
0)"
0,"
0/"
02"
05"
08"
0;"
0>"
0A"
0D"
0G"
0J"
0M"
0P"
0S"
0V"
0G
0I
0K
0M
0O
0Q
0S
0U
0W
0Z
0]
0`
0c
0f
0i
0l
0o
0r
0u
0x
0{
0~
0#"
0&"
b1000001010011100100010000100000001100000011000000100000001001100010000001000110010001100010000001111010011001010111001001101111 ]"
b0 Z"
b0 Y"
b0 "
b0 %
#40000
1q
b10001 +
1}
b10001000 !
b10001000 .
0b
b1110111 ,
0n
0+"
b11101110 )
07"
0C"
0O"
1:
b10001000 -
1F
0L"
b1100110 (
0X"
0J
0N
0R
b1010101 *
0V
00
03
0<
0?
0*"
0-"
06"
09"
0B"
0E"
0N"
0Q"
0X
0[
0d
0g
0p
0s
0|
0!"
12
18
1>
1D
1,"
12"
18"
1>"
1D"
1J"
1P"
1V"
1I
1M
1Q
1U
1Z
1`
1f
1l
1r
1x
1~
1&"
b100000101001110010001000010000001000001010000010010000000100110001000000100001101000011 ]"
b11001100 ["
b10101010 Z"
b10001000 Y"
b11001100 #
b11001100 &
b10101010 "
b10101010 %
#50000
1n
0q
b11111111 ,
1b
b0 +
0}
0F
1+"
1C"
1X"
b0 -
0:
b11111111 )
17"
1L"
b11111111 (
1O"
1J
1N
0P
b1111 *
0T
b11111111 !
b11111111 .
10
13
0B
0E
1*"
1-"
0<"
0?"
1B"
1E"
0T"
0W"
1X
1[
0j
0m
1p
1s
0$"
0'"
02
08
1;
1A
0,"
02"
15"
1;"
0D"
0J"
1M"
1S"
0I
0M
1O
1S
0Z
0`
1c
1i
0r
0x
1{
1#"
b1001111010100100010000001000110001100000010000001111100001000000011000001000110 ]"
b1 \"
b1111 ["
b11110000 Z"
b11111111 Y"
b1 $
b1 '
b1111 #
b1111 &
b11110000 "
b11110000 %
#60000
1q
1t
1w
1z
b0 !
b0 .
1}
1""
1%"
b11111111 +
1("
0+"
0."
01"
04"
0C"
0F"
0I"
0L"
07"
0:"
0="
b0 )
0@"
0O"
0R"
0U"
b0 (
0X"
1P
1R
1T
b11111111 *
1V
00
03
06
09
0*"
0-"
00"
03"
0B"
0E"
0H"
0K"
0X
0[
0^
0a
0p
0s
0v
0y
0;
0>
0A
0D
05"
08"
0;"
0>"
0M"
0P"
0S"
0V"
0O
0Q
0S
0U
0c
0f
0i
0l
0{
0~
0#"
0&"
b10011110101001000100000001100000011000000100000011111000010000000110000001100000010000001111010011001010111001001101111 ]"
b0 ["
b0 Z"
b0 Y"
b0 #
b0 &
b0 "
b0 %
#70000
0q
0w
0}
0%"
b11111111 !
b11111111 .
0t
0z
0""
b0 +
0("
1+"
11"
17"
1="
1C"
1I"
1O"
1U"
1."
14"
1:"
b11111111 )
1@"
1F"
1L"
1R"
b11111111 (
1X"
0J
0N
0R
b1010101 *
0V
10
16
1<
1B
1*"
10"
16"
1<"
1B"
1H"
1N"
1T"
1X
1^
1d
1j
1p
1v
1|
1$"
12
18
1>
1D
1,"
12"
18"
1>"
1D"
1J"
1P"
1V"
1I
1M
1Q
1U
1Z
1`
1f
1l
1r
1x
1~
1&"
b1001111010100100010000001000001010000010010000001111100001000000011010100110101 ]"
b1010101 ["
b10101010 Z"
b11111111 Y"
b1010101 #
b1010101 &
b10101010 "
b10101010 %
#80000
0H
0L
0P
b0 *
0T
00
06
0<
0B
0*"
00"
06"
0<"
0B"
0H"
0N"
0T"
0X
0^
0d
0j
0p
0v
0|
0$"
1/
15
1;
1A
1)"
1/"
15"
1;"
1A"
1G"
1M"
1S"
1G
1K
1O
1S
1W
1]
1c
1i
1o
1u
1{
1#"
b1001111010100100010000001000110010001100010000001111100001000000011000000110000 ]"
b0 ["
b11111111 Z"
b0 #
b0 &
b11111111 "
b11111111 %
#90000
1H
1L
1P
b1010101 *
1T
10
16
1<
1B
1*"
10"
16"
1<"
1B"
1H"
1N"
1T"
1X
1^
1d
1j
1p
1v
1|
1$"
0/
05
0;
0A
0)"
0/"
05"
0;"
0A"
0G"
0M"
0S"
0G
0K
0O
0S
0W
0]
0c
0i
0o
0u
0{
0#"
b10011110101001000100000010000010100000100100000011111000010000000110101001101010010000000111101001000000100011001000110 ]"
b1010101 ["
b10101010 Z"
b1010101 #
b1010101 &
b10101010 "
b10101010 %
#100000
0\
0b
0h
0n
b0 !
b0 .
0Y
0_
0e
b0 ,
0k
14
1:
1@
1F
0F"
0L"
0R"
0X"
11
17
1=
b11111111 -
1C
0C"
0I"
0O"
b0 (
0U"
0H
0L
0P
b0 *
0T
13
19
1?
1E
1-"
13"
19"
1?"
1E"
1K"
1Q"
1W"
1[
1a
1g
1m
1s
1y
1!"
1'"
1/
15
1;
1A
1)"
1/"
15"
1;"
1A"
1G"
1M"
1S"
1G
1K
1O
1S
1W
1]
1c
1i
1o
1u
1{
1#"
b1011000010011110101001000100000010001100100011000100000010111100010000001000110010001100010000001111010011001010111001001101111 ]"
b10 \"
b11111111 ["
b11111111 Z"
b0 Y"
b10 $
b10 '
b11111111 #
b11111111 &
b11111111 "
b11111111 %
#110000
1\
1b
1h
1n
b11111111 !
b11111111 .
1Y
1_
1e
b11111111 ,
1k
04
0:
0@
0F
1F"
1L"
1R"
1X"
01
07
0=
b0 -
0C
1C"
1I"
1O"
b11111111 (
1U"
1H
1L
1P
b1010101 *
1T
03
09
0?
0E
0-"
03"
09"
0?"
0E"
0K"
0Q"
0W"
0[
0a
0g
0m
0s
0y
0!"
0'"
0/
05
0;
0A
0)"
0/"
05"
0;"
0A"
0G"
0M"
0S"
0G
0K
0O
0S
0W
0]
0c
0i
0o
0u
0{
0#"
b101100001001111010100100010000001000001010000010010000001011110001000000011010100110101 ]"
b1010101 ["
b10101010 Z"
b11111111 Y"
b1010101 #
b1010101 &
b10101010 "
b10101010 %
#120000
1J
1N
1R
b11111111 *
1V
13
19
1?
1E
1-"
13"
19"
1?"
1E"
1K"
1Q"
1W"
1[
1a
1g
1m
1s
1y
1!"
1'"
02
08
0>
0D
0,"
02"
08"
0>"
0D"
0J"
0P"
0V"
0I
0M
0Q
0U
0Z
0`
0f
0l
0r
0x
0~
0&"
b101100001001111010100100010000000110000001100000010000001011110001000000100011001000110 ]"
b11111111 ["
b0 Z"
b11111111 #
b11111111 &
b0 "
b0 %
#130000
0H
0J
0L
0N
0P
0R
0T
b0 *
0V
00
03
06
09
0<
0?
0B
0E
0*"
0-"
00"
03"
06"
09"
0<"
0?"
0B"
0E"
0H"
0K"
0N"
0Q"
0T"
0W"
0X
0[
0^
0a
0d
0g
0j
0m
0p
0s
0v
0y
0|
0!"
0$"
0'"
1/
12
15
18
1;
1>
1A
1D
1)"
1,"
1/"
12"
15"
18"
1;"
1>"
1A"
1D"
1G"
1J"
1M"
1P"
1S"
1V"
1G
1I
1K
1M
1O
1Q
1S
1U
1W
1Z
1]
1`
1c
1f
1i
1l
1o
1r
1u
1x
1{
1~
1#"
1&"
b101100001001111010100100010000001000110010001100010000001011110001000000011000000110000 ]"
b0 ["
b11111111 Z"
b0 #
b0 &
b11111111 "
b11111111 %
#140000
0\
0b
0h
b1010101 ,
0n
b0 !
b0 .
1q
1w
1}
b1010101 +
1%"
14
1:
1@
b10101010 -
1F
0F"
0L"
0R"
0X"
0+"
01"
07"
b10101010 )
0="
0C"
0I"
0O"
b0 (
0U"
1H
1L
1P
b1010101 *
1T
13
19
1?
1E
1-"
13"
19"
1?"
1E"
1K"
1Q"
1W"
1[
1a
1g
1m
1s
1y
1!"
1'"
0/
05
0;
0A
0)"
0/"
05"
0;"
0A"
0G"
0M"
0S"
0G
0K
0O
0S
0W
0]
0c
0i
0o
0u
0{
0#"
b101100001001111010100100010000001110011011000010110110101100101001000000110100101101110011100000111010101110100011100110010000001111010011001010111001001101111 ]"
b10101010 ["
b10101010 Z"
b0 Y"
b10101010 #
b10101010 &
b10101010 "
b10101010 %
#150000
1\
1b
1h
b11111111 ,
1n
1t
1z
1""
b11111111 +
1("
04
0:
0@
b0 -
0F
0."
04"
0:"
b0 )
0@"
1J
1N
1R
b11111111 *
1V
b11111111 !
b11111111 .
03
09
0?
0E
0-"
03"
09"
0?"
0E"
0K"
0Q"
0W"
0[
0a
0g
0m
0s
0y
0!"
0'"
02
08
0>
0D
0,"
02"
08"
0>"
0D"
0J"
0P"
0V"
0I
0M
0Q
0U
0Z
0`
0f
0l
0r
0x
0~
0&"
b100111001001111010101000010000000110000001100000010000000111101001000000100011001000110 ]"
b11 \"
b0 ["
b0 Z"
b11111111 Y"
b11 $
b11 '
b0 #
b0 &
b0 "
b0 %
#160000
b0 !
b0 .
0q
0t
0w
0z
0}
0""
0%"
b0 +
0("
1+"
1."
11"
14"
17"
1:"
1="
b11111111 )
1@"
1C"
1F"
1I"
1L"
1O"
1R"
1U"
b11111111 (
1X"
0H
0J
0L
0N
0P
0R
0T
b0 *
0V
1/
12
15
18
1;
1>
1A
1D
1)"
1,"
1/"
12"
15"
18"
1;"
1>"
1A"
1D"
1G"
1J"
1M"
1P"
1S"
1V"
1G
1I
1K
1M
1O
1Q
1S
1U
1W
1Z
1]
1`
1c
1f
1i
1l
1o
1r
1u
1x
1{
1~
1#"
1&"
b100111001001111010101000010000001000110010001100010000000111101001000000011000000110000 ]"
b11111111 Z"
b0 Y"
b11111111 "
b11111111 %
#170000
b1010101 !
b1010101 .
1q
1w
1}
b1010101 +
1%"
0+"
01"
07"
b10101010 )
0="
0C"
0I"
0O"
b10101010 (
0U"
1H
1L
1P
b1010101 *
1T
0/
05
0;
0A
0)"
0/"
05"
0;"
0A"
0G"
0M"
0S"
0G
0K
0O
0S
0W
0]
0c
0i
0o
0u
0{
0#"
b100111001001111010101000010000001000001010000010010000000111101001000000011010100110101 ]"
b10101010 Z"
b1010101 Y"
b10101010 "
b10101010 %
#180000
b10101010 !
b10101010 .
0q
1t
0w
1z
0}
1""
0%"
b10101010 +
1("
1+"
0."
11"
04"
17"
0:"
1="
b1010101 )
0@"
1C"
0F"
1I"
0L"
1O"
0R"
1U"
b1010101 (
0X"
0H
1J
0L
1N
0P
1R
0T
b10101010 *
1V
1/
02
15
08
1;
0>
1A
0D
1)"
0,"
1/"
02"
15"
08"
1;"
0>"
1A"
0D"
1G"
0J"
1M"
0P"
1S"
0V"
1G
0I
1K
0M
1O
0Q
1S
0U
1W
0Z
1]
0`
1c
0f
1i
0l
1o
0r
1u
0x
1{
0~
1#"
0&"
b100111001001111010101000010000000110101001101010010000000111101001000000100000101000001 ]"
b1010101 Z"
b10101010 Y"
b1010101 "
b1010101 %
#190000
b1111 !
b1111 .
1q
1w
0""
b1111 +
0("
0+"
01"
1:"
b11110000 )
1@"
0C"
0I"
1R"
b11110000 (
1X"
1H
1L
0R
b1111 *
0V
0/
05
1>
1D
0)"
0/"
18"
1>"
0A"
0G"
1P"
1V"
0G
0K
1Q
1U
0W
0]
1f
1l
0o
0u
1~
1&"
b100111001001111010101000010000001000110001100000010000000111101001000000011000001000110 ]"
b11110000 Z"
b1111 Y"
b11110000 "
b11110000 %
#200000
0e
0h
0k
0n
0Y
0\
0_
b0 ,
0b
0q
0t
0w
b0 +
0z
1=
1@
1C
1F
0O"
0R"
0U"
b0 (
0X"
11
14
17
b11111111 -
1:
1+"
1."
11"
b11111111 )
14"
0H
0J
0L
b0 *
0N
b0 !
b0 .
10
13
16
19
1<
1?
1B
1E
1*"
1-"
10"
13"
16"
19"
1<"
1?"
1B"
1E"
1H"
1K"
1N"
1Q"
1T"
1W"
1X
1[
1^
1a
1d
1g
1j
1m
1p
1s
1v
1y
1|
1!"
1$"
1'"
1/
12
15
18
1)"
1,"
1/"
12"
1A"
1D"
1G"
1J"
1G
1I
1K
1M
1W
1Z
1]
1`
1o
1r
1u
1x
b100111001000001010011100100010000100000010001100100011000100000001001100010000001000110010001100010000000111101001000000011000000110000 ]"
b100 \"
b11111111 ["
b11111111 Z"
b0 Y"
b100 $
b100 '
b11111111 #
b11111111 &
b11111111 "
b11111111 %
