RTL/shifter/LR_shifter.v
`timescale 1ns/1ps

// Shifts left or right by 1 bit
// dir=0 → left shift (multiply by 2)
// dir=1 → right shift (divide by 2)

module LR_shifter(
    input  wire [7:0] a,
    input  wire       dir,
    output wire [7:0] result
);
    wire [7:0] shift_left;
    wire [7:0] shift_right;
    wire [7:0] mux_out;

    // Left shift: each bit moves one position left, LSB gets 0
    assign shift_left[7] = a[6];
    assign shift_left[6] = a[5];
    assign shift_left[5] = a[4];
    assign shift_left[4] = a[3];
    assign shift_left[3] = a[2];
    assign shift_left[2] = a[1];
    assign shift_left[1] = a[0];
    assign shift_left[0] = 1'b0;

    // Right shift: each bit moves one position right, MSB gets 0
    assign shift_right[7] = 1'b0;
    assign shift_right[6] = a[7];
    assign shift_right[5] = a[6];
    assign shift_right[4] = a[5];
    assign shift_right[3] = a[4];
    assign shift_right[2] = a[3];
    assign shift_right[1] = a[2];
    assign shift_right[0] = a[1];

    // Mux selects left or right based on dir
    assign result = dir ? shift_right : shift_left;

endmodule

RTL/testbench/LR_shifter_tb.v
`timescale 1ns/1ps

module LR_shifter_tb;

    reg  [7:0] a;
    reg        dir;
    wire [7:0] result;

    // Declare here — NOT inside initial block
    reg [7:0] after_shl;

    LR_shifter uut(
        .a(a),
        .dir(dir),
        .result(result)
    );

    task check;
        input [7:0] expected;
        input [7:0] in_a;
        input       in_dir;
        input [8*20-1:0] label;
        begin
            #10;
            if (result === expected)
                $display("PASS | %-25s | in=%08b out=%08b",
                          label, in_a, result);
            else
                $display("FAIL | %-25s | in=%08b got=%08b expected=%08b",
                          label, in_a, result, expected);
        end
    endtask

    initial begin
        $dumpfile("LR_shifter.vcd");
        $dumpvars(0, LR_shifter_tb);

        // ── LEFT SHIFT tests (dir=0) ──────────────────────────
        a = 8'b00000001; dir = 0;
        check(8'b00000010, a, dir, "SHL 00000001");

        a = 8'b00000010; dir = 0;
        check(8'b00000100, a, dir, "SHL 00000010");

        a = 8'b00010000; dir = 0;
        check(8'b00100000, a, dir, "SHL 00010000");

        a = 8'b01000000; dir = 0;
        check(8'b10000000, a, dir, "SHL 01000000");

        a = 8'b10000000; dir = 0;
        check(8'b00000000, a, dir, "SHL 10000000 MSB lost");

        a = 8'b00000101; dir = 0;
        check(8'b00001010, a, dir, "SHL 5 = 10");

        a = 8'b00001010; dir = 0;
        check(8'b00010100, a, dir, "SHL 10 = 20");

        a = 8'b00110010; dir = 0;
        check(8'b01100100, a, dir, "SHL 50 = 100");

        a = 8'b00000000; dir = 0;
        check(8'b00000000, a, dir, "SHL 0 = 0");

        a = 8'b11111111; dir = 0;
        check(8'b11111110, a, dir, "SHL 11111111");

        // ── RIGHT SHIFT tests (dir=1) ─────────────────────────
        a = 8'b10000000; dir = 1;
        check(8'b01000000, a, dir, "SHR 10000000");

        a = 8'b01000000; dir = 1;
        check(8'b00100000, a, dir, "SHR 01000000");

        a = 8'b00000010; dir = 1;
        check(8'b00000001, a, dir, "SHR 00000010");

        a = 8'b00000001; dir = 1;
        check(8'b00000000, a, dir, "SHR 00000001 LSB lost");

        a = 8'b00001010; dir = 1;
        check(8'b00000101, a, dir, "SHR 10 = 5");

        a = 8'b00010100; dir = 1;
        check(8'b00001010, a, dir, "SHR 20 = 10");

        a = 8'b01100100; dir = 1;
        check(8'b00110010, a, dir, "SHR 100 = 50");

        a = 8'b00000000; dir = 1;
        check(8'b00000000, a, dir, "SHR 0 = 0");

        a = 8'b11111111; dir = 1;
        check(8'b01111111, a, dir, "SHR 11111111");

        // ── SHL then SHR relationship ─────────────────────────
        a = 8'b00001010; dir = 0; #10;
        after_shl = result;         // save result of SHL
        a = after_shl; dir = 1;
        check(8'b00001010, after_shl, dir, "SHL then SHR");

        $display("Barrel shifter testbench complete");
        $finish;
    end

endmodule

RTL/vvp_gtk/LR_shifter.vcd
$date
	Sun Sep 27 02:12:05 2026
$end
$version
	Icarus Verilog
$end
$timescale
	1ps
$end
$scope module LR_shifter_tb $end
$var wire 8 ! result [7:0] $end
$var reg 8 " a [7:0] $end
$var reg 8 # after_shl [7:0] $end
$var reg 1 $ dir $end
$scope module uut $end
$var wire 8 % a [7:0] $end
$var wire 1 $ dir $end
$var wire 8 & shift_right [7:0] $end
$var wire 8 ' shift_left [7:0] $end
$var wire 8 ( result [7:0] $end
$upscope $end
$scope task check $end
$var reg 8 ) expected [7:0] $end
$var reg 8 * in_a [7:0] $end
$var reg 1 + in_dir $end
$var reg 160 , label [159:0] $end
$upscope $end
$upscope $end
$enddefinitions $end
$comment Show the parameter values. $end
$dumpall
$end
#0
$dumpvars
b10100110100100001001100001000000011000000110000001100000011000000110000001100000011000000110001 ,
0+
b1 *
b10 )
b10 (
b10 '
b0 &
b1 %
0$
bx #
b1 "
b10 !
$end
#10000
b100 !
b100 (
b100 '
b1 &
b10100110100100001001100001000000011000000110000001100000011000000110000001100000011000100110000 ,
b10 *
b100 )
b10 "
b10 %
#20000
b100000 !
b100000 (
b100000 '
b1000 &
b10100110100100001001100001000000011000000110000001100000011000100110000001100000011000000110000 ,
b10000 *
b100000 )
b10000 "
b10000 %
#30000
b10000000 !
b10000000 (
b10000000 '
b100000 &
b10100110100100001001100001000000011000000110001001100000011000000110000001100000011000000110000 ,
b1000000 *
b10000000 )
b1000000 "
b1000000 %
#40000
b0 !
b0 (
b0 '
b1000000 &
b100100001001100001000000011000100110000001100000011000000110000001100000011000000110000001000000100110101010011010000100010000001101100011011110111001101110100 ,
b10000000 *
b0 )
b10000000 "
b10000000 %
#50000
b1010 !
b1010 (
b1010 '
b10 &
b1010011010010000100110000100000001101010010000000111101001000000011000100110000 ,
b101 *
b1010 )
b101 "
b101 %
#60000
b10100 !
b10100 (
b10100 '
b101 &
b101001101001000010011000010000000110001001100000010000000111101001000000011001000110000 ,
b1010 *
b10100 )
b1010 "
b1010 %
#70000
b1100100 !
b1100100 (
b1100100 '
b11001 &
b10100110100100001001100001000000011010100110000001000000011110100100000001100010011000000110000 ,
b110010 *
b1100100 )
b110010 "
b110010 %
#80000
b0 !
b0 (
b0 '
b0 &
b10100110100100001001100001000000011000000100000001111010010000000110000 ,
b0 *
b0 )
b0 "
b0 %
#90000
b11111110 !
b11111110 (
b11111110 '
b1111111 &
b10100110100100001001100001000000011000100110001001100010011000100110001001100010011000100110001 ,
b11111111 *
b11111110 )
b11111111 "
b11111111 %
#100000
b1000000 !
b1000000 (
b0 '
b1000000 &
b10100110100100001010010001000000011000100110000001100000011000000110000001100000011000000110000 ,
1+
b10000000 *
b1000000 )
1$
b10000000 "
b10000000 %
#110000
b100000 !
b100000 (
b10000000 '
b100000 &
b10100110100100001010010001000000011000000110001001100000011000000110000001100000011000000110000 ,
b1000000 *
b100000 )
b1000000 "
b1000000 %
#120000
b1 !
b1 (
b100 '
b1 &
b10100110100100001010010001000000011000000110000001100000011000000110000001100000011000100110000 ,
b10 *
b1 )
b10 "
b10 %
#130000
b0 !
b0 (
b10 '
b0 &
b100100001010010001000000011000000110000001100000011000000110000001100000011000000110001001000000100110001010011010000100010000001101100011011110111001101110100 ,
b1 *
b0 )
b1 "
b1 %
#140000
b101 !
b101 (
b10100 '
b101 &
b1010011010010000101001000100000001100010011000000100000001111010010000000110101 ,
b1010 *
b101 )
b1010 "
b1010 %
#150000
b1010 !
b1010 (
b101000 '
b1010 &
b101001101001000010100100010000000110010001100000010000000111101001000000011000100110000 ,
b10100 *
b1010 )
b10100 "
b10100 %
#160000
b110010 !
b110010 (
b11001000 '
b110010 &
b10100110100100001010010001000000011000100110000001100000010000000111101001000000011010100110000 ,
b1100100 *
b110010 )
b1100100 "
b1100100 %
#170000
b0 !
b0 (
b0 '
b0 &
b10100110100100001010010001000000011000000100000001111010010000000110000 ,
b0 *
b0 )
b0 "
b0 %
#180000
b1111111 !
b1111111 (
b11111110 '
b1111111 &
b10100110100100001010010001000000011000100110001001100010011000100110001001100010011000100110001 ,
b11111111 *
b1111111 )
b11111111 "
b11111111 %
#190000
b10100 !
b10100 (
b10100 '
b101 &
0$
b1010 "
b1010 %
#200000
b1010 !
b1010 (
b101000 '
b1010 &
b10100110100100001001100001000000111010001101000011001010110111000100000010100110100100001010010 ,
b10100 *
b1010 )
1$
b10100 "
b10100 %
b10100 #
