RTL/gate/gates.v
`timescale 1ns/1ps

module and_gate(a,b,y);
    input wire a,b;
    output wire y;
    assign y = a&b;
endmodule  

module or_gate(a,b,y);
    input wire a,b;
    output wire y;
    assign y = a|b;
endmodule    

module xor_gate(a,b,y);
    input wire a,b;
    output wire y;
    assign y = a^b;
endmodule


module not_gate(a,y);
    input wire a;
    output wire y;
    assign y = ~a;
endmodule 


module nand_gate(a,b,y);
    input wire a,b;
    output wire y;
    assign y = ~(a&b);
endmodule 


module nor_gate(a,b,y);
    input wire a,b;
    output wire y;
    assign y = ~(a|b);
endmodule

RTL/adder/adder.v
module half_adder(a,b,sum,carry);
    input wire a,b;
    output wire sum, carry;

    and_gate AG_01(.a(a), .b(b), .y(carry));
    xor_gate XG_01(.a(a), .b(b), .y(sum));
endmodule

module full_adder(a,b,cin,sum,cout);
    input wire a,b,cin;
    output wire sum,cout;

    wire sum1, carry1, carry2;
    half_adder HA_01(.a(a), .b(b), .sum(sum1), .carry(carry1));
    half_adder HA_02(.a(sum1),.b(cin), .sum(sum), .carry(carry2));

    or_gate OR_01(.a(carry1), .b(carry2), .y(cout));

endmodule

RTL/adder/ripple_carry_adder.v
`timescale 1ns/1ps

module ripple_carry_adder(
    input  wire [7:0] a,
    input  wire [7:0] b,
    input  wire b_invert,
    input  wire cin,
    output wire cout,
    output wire zero_flag,
    output wire negative_flag,
    output wire overflow_flag,
    output wire [7:0] result
);

    wire [7:0] b_modified;

    // When b_invert is high, XOR flips every bit of b (needed for subtraction).
    // When low, b passes straight through untouched.
    
    xor_gate bx0(.a(b[0]), .b(b_invert), .y(b_modified[0]));
    xor_gate bx1(.a(b[1]), .b(b_invert), .y(b_modified[1]));
    xor_gate bx2(.a(b[2]), .b(b_invert), .y(b_modified[2]));
    xor_gate bx3(.a(b[3]), .b(b_invert), .y(b_modified[3]));
    xor_gate bx4(.a(b[4]), .b(b_invert), .y(b_modified[4]));
    xor_gate bx5(.a(b[5]), .b(b_invert), .y(b_modified[5]));
    xor_gate bx6(.a(b[6]), .b(b_invert), .y(b_modified[6]));
    xor_gate bx7(.a(b[7]), .b(b_invert), .y(b_modified[7]));

     wire [6:0] carry;

    // Internal carry ripple chain between stages (bit 0 up to bit 6)
    full_adder fa0(.a(a[0]), .b(b_modified[0]), .cin(cin), .sum(result[0]),
     .cout(carry[0]));
        
    full_adder fa1(.a(a[1]), .b(b_modified[1]), .cin(carry[0]), .sum(result[1]), 
    .cout(carry[1]));
        
    full_adder fa2(.a(a[2]), .b(b_modified[2]), .cin(carry[1]), .sum(result[2]), 
    .cout(carry[2]));
        
    full_adder fa3(.a(a[3]), .b(b_modified[3]), .cin(carry[2]), .sum(result[3]),
    .cout(carry[3]));
    
    full_adder fa4(.a(a[4]), .b(b_modified[4]), .cin(carry[3]), .sum(result[4]),
    .cout(carry[4]));
   
    full_adder fa5(.a(a[5]), .b(b_modified[5]), .cin(carry[4]), .sum(result[5]),
    .cout(carry[5]));  
         
  
    full_adder fa6(.a(a[6]), .b(b_modified[6]), .cin(carry[5]), .sum(result[6]),
    .cout(carry[6]));

    full_adder fa7(.a(a[7]), .b(b_modified[7]), .cin(carry[6]),
    .sum(result[7]), .cout(cout));
    
    // Status flags: 1. Z: high if the result evaluates to all zeros 
                //   2.N: high if the sign bit (MSB) is 1 (two's complement negative)
    assign zero_flag     = (result == 8'b0);
    assign negative_flag = result[7];

    // Signed overflow check: Flags when carry-in to the sign bit (carry[6])
    // doesn't match carry-out (cout)

   xor_gate overflow_xor(.a(carry[6]), .b(cout), .y(overflow_flag));
        
endmodule

RTL/testbench/ripple_carry_adder_tb.v
`timescale 1ns/1ps

module ripple_carry_adder_tb;

    reg  [7:0] a, b;
    reg  b_invert, cin;
    wire [7:0] result;
    wire cout, zero_flag, negative_flag, overflow_flag;

    ripple_carry_adder uut(
        .a(a), .b(b),
        .b_invert(b_invert),
        .cin(cin),
        .result(result),
        .cout(cout),
        .zero_flag(zero_flag),
        .negative_flag(negative_flag),
        .overflow_flag(overflow_flag)
    );

    // Simple test helper: sample after signals settle, then check against expected output
    task check;
        input [7:0] expected_result;
        input expected_zero;
        input [63:0] test_name;
        begin
            #5;
            if (result === expected_result && zero_flag === expected_zero)
                $display("PASS | %s | result=%0d", test_name, result);
            else
                $display("FAIL | %s | got=%0d expected=%0d",
                          test_name, result, expected_result);
        end
    endtask

    initial begin
        $dumpfile("rca.vcd");
        $dumpvars(0, ripple_carry_adder_tb);

        // Standard addition (A + B): pass B straight through without an extra carry-in
        a=10;  b=20;  b_invert=0; cin=0; #10;
        check(30,  0, "ADD 10+20");

        a=0;   b=0;   b_invert=0; cin=0; #10;
        check(0,   1, "ADD 0+0 zero flag");

        // 8-bit wrap-around: 255 + 1 wraps to 0 with a carry-out bit set
        a=255; b=1;   b_invert=0; cin=0; #10;
        check(0,   1, "ADD 255+1 overflow");
        #1; $display("carry_out=%0b (expect 1)", cout);

        // Subtraction (A - B): invert B and assert cin to form two's complement (~B + 1)
        a=20;  b=10;  b_invert=1; cin=1; #10;
        check(10,  0, "SUB 20-10");

        a=5;   b=5;   b_invert=1; cin=1; #10;
        check(0,   1, "SUB 5-5 zero flag");

        a=100; b=50;  b_invert=1; cin=1; #10;
        check(50,  0, "SUB 100-50");

        // Increment: leave B at zero and inject a +1 carry directly via cin
        a=5;   b=0;   b_invert=0; cin=1; #10;
        check(6,   0, "INC 5");

        a=255; b=0;   b_invert=0; cin=1; #10;
        check(0,   1, "INC 255 wraps to 0");

        // Decrement: adding 0xFF (-1 in 2's complement) naturally drops the value by 1
        a=5;   b=8'hFF; b_invert=0; cin=0; #10;
        check(4,   0, "DEC 5");

        a=1;   b=8'hFF; b_invert=0; cin=0; #10;
        check(0,   1, "DEC 1 gives 0");

        // Negate: evaluate 0 - B by taking two's complement of B
        a=0;   b=5;   b_invert=1; cin=1; #10;
        check(251, 0, "NEG 5 = 251 (which is -5 in 8-bit)");

        a=0;   b=1;   b_invert=1; cin=1; #10;
        check(255, 0, "NEG 1 = 255 (which is -1 in 8-bit)");
        #1; $display("      negative_flag=%0b (expect 1)", negative_flag);

        // Magnitude compare (A vs B): runs a subtraction under the hood to evaluate condition flags
        a=10;  b=10;  b_invert=1; cin=1; #10;
        #1; $display("CMP 10==10 | zero=%0b (expect 1)", zero_flag);

        a=10;  b=5;   b_invert=1; cin=1; #10;
        #1; $display("CMP 10>5   | zero=%0b neg=%0b (expect 0,0)",
                      zero_flag, negative_flag);

        a=5;   b=10;  b_invert=1; cin=1; #10;
        #1; $display("CMP 5<10   | neg=%0b (expect 1)", negative_flag);

        // Left shift / Multiply by 2: add the register to itself (A + A)
        a=5;   b=5;   b_invert=0; cin=0; #10;
        check(10,  0, "MUL2 5x2=10");

        a=64;  b=64;  b_invert=0; cin=0; #10;
        check(128, 0, "MUL2 64x2=128");

        a=200; b=200; b_invert=0; cin=0; #10;
        #1; $display("MUL2 200x2=400 | result=%0d cout=%0b (overflow)",
                      result, cout);

        // Constant arithmetic tests
        a=10;  b=8'd7; b_invert=0; cin=0; #10;
        check(17,  0, "ADD_CONST 10+7");

        a=20;  b=8'd3; b_invert=1; cin=1; #10;
        check(17,  0, "SUB_CONST 20-3");

        
        $finish;
    end

endmodule

RTL/vvp_gtk/rca.vcd
$date
	Sat Sep 26 17:55:42 2026
$end
$version
	Icarus Verilog
$end
$timescale
	1ps
$end
$scope module ripple_carry_adder_tb $end
$var wire 1 ! zero_flag $end
$var wire 8 " result [7:0] $end
$var wire 1 # overflow_flag $end
$var wire 1 $ negative_flag $end
$var wire 1 % cout $end
$var reg 8 & a [7:0] $end
$var reg 8 ' b [7:0] $end
$var reg 1 ( b_invert $end
$var reg 1 ) cin $end
$scope module uut $end
$var wire 8 * a [7:0] $end
$var wire 8 + b [7:0] $end
$var wire 1 ( b_invert $end
$var wire 1 ) cin $end
$var wire 1 ! zero_flag $end
$var wire 8 , result [7:0] $end
$var wire 1 # overflow_flag $end
$var wire 1 $ negative_flag $end
$var wire 1 % cout $end
$var wire 7 - carry [6:0] $end
$var wire 8 . b_modified [7:0] $end
$scope module bx0 $end
$var wire 1 / a $end
$var wire 1 ( b $end
$var wire 1 0 y $end
$upscope $end
$scope module bx1 $end
$var wire 1 1 a $end
$var wire 1 ( b $end
$var wire 1 2 y $end
$upscope $end
$scope module bx2 $end
$var wire 1 3 a $end
$var wire 1 ( b $end
$var wire 1 4 y $end
$upscope $end
$scope module bx3 $end
$var wire 1 5 a $end
$var wire 1 ( b $end
$var wire 1 6 y $end
$upscope $end
$scope module bx4 $end
$var wire 1 7 a $end
$var wire 1 ( b $end
$var wire 1 8 y $end
$upscope $end
$scope module bx5 $end
$var wire 1 9 a $end
$var wire 1 ( b $end
$var wire 1 : y $end
$upscope $end
$scope module bx6 $end
$var wire 1 ; a $end
$var wire 1 ( b $end
$var wire 1 < y $end
$upscope $end
$scope module bx7 $end
$var wire 1 = a $end
$var wire 1 ( b $end
$var wire 1 > y $end
$upscope $end
$scope module fa0 $end
$var wire 1 ? a $end
$var wire 1 @ b $end
$var wire 1 ) cin $end
$var wire 1 A sum1 $end
$var wire 1 B sum $end
$var wire 1 C cout $end
$var wire 1 D carry2 $end
$var wire 1 E carry1 $end
$scope module HA_01 $end
$var wire 1 ? a $end
$var wire 1 @ b $end
$var wire 1 A sum $end
$var wire 1 E carry $end
$scope module AG_01 $end
$var wire 1 ? a $end
$var wire 1 @ b $end
$var wire 1 E y $end
$upscope $end
$scope module XG_01 $end
$var wire 1 ? a $end
$var wire 1 @ b $end
$var wire 1 A y $end
$upscope $end
$upscope $end
$scope module HA_02 $end
$var wire 1 A a $end
$var wire 1 ) b $end
$var wire 1 B sum $end
$var wire 1 D carry $end
$scope module AG_01 $end
$var wire 1 A a $end
$var wire 1 ) b $end
$var wire 1 D y $end
$upscope $end
$scope module XG_01 $end
$var wire 1 A a $end
$var wire 1 ) b $end
$var wire 1 B y $end
$upscope $end
$upscope $end
$scope module OR_01 $end
$var wire 1 E a $end
$var wire 1 D b $end
$var wire 1 C y $end
$upscope $end
$upscope $end
$scope module fa1 $end
$var wire 1 F a $end
$var wire 1 G b $end
$var wire 1 H cin $end
$var wire 1 I sum1 $end
$var wire 1 J sum $end
$var wire 1 K cout $end
$var wire 1 L carry2 $end
$var wire 1 M carry1 $end
$scope module HA_01 $end
$var wire 1 F a $end
$var wire 1 G b $end
$var wire 1 I sum $end
$var wire 1 M carry $end
$scope module AG_01 $end
$var wire 1 F a $end
$var wire 1 G b $end
$var wire 1 M y $end
$upscope $end
$scope module XG_01 $end
$var wire 1 F a $end
$var wire 1 G b $end
$var wire 1 I y $end
$upscope $end
$upscope $end
$scope module HA_02 $end
$var wire 1 I a $end
$var wire 1 H b $end
$var wire 1 J sum $end
$var wire 1 L carry $end
$scope module AG_01 $end
$var wire 1 I a $end
$var wire 1 H b $end
$var wire 1 L y $end
$upscope $end
$scope module XG_01 $end
$var wire 1 I a $end
$var wire 1 H b $end
$var wire 1 J y $end
$upscope $end
$upscope $end
$scope module OR_01 $end
$var wire 1 M a $end
$var wire 1 L b $end
$var wire 1 K y $end
$upscope $end
$upscope $end
$scope module fa2 $end
$var wire 1 N a $end
$var wire 1 O b $end
$var wire 1 P cin $end
$var wire 1 Q sum1 $end
$var wire 1 R sum $end
$var wire 1 S cout $end
$var wire 1 T carry2 $end
$var wire 1 U carry1 $end
$scope module HA_01 $end
$var wire 1 N a $end
$var wire 1 O b $end
$var wire 1 Q sum $end
$var wire 1 U carry $end
$scope module AG_01 $end
$var wire 1 N a $end
$var wire 1 O b $end
$var wire 1 U y $end
$upscope $end
$scope module XG_01 $end
$var wire 1 N a $end
$var wire 1 O b $end
$var wire 1 Q y $end
$upscope $end
$upscope $end
$scope module HA_02 $end
$var wire 1 Q a $end
$var wire 1 P b $end
$var wire 1 R sum $end
$var wire 1 T carry $end
$scope module AG_01 $end
$var wire 1 Q a $end
$var wire 1 P b $end
$var wire 1 T y $end
$upscope $end
$scope module XG_01 $end
$var wire 1 Q a $end
$var wire 1 P b $end
$var wire 1 R y $end
$upscope $end
$upscope $end
$scope module OR_01 $end
$var wire 1 U a $end
$var wire 1 T b $end
$var wire 1 S y $end
$upscope $end
$upscope $end
$scope module fa3 $end
$var wire 1 V a $end
$var wire 1 W b $end
$var wire 1 X cin $end
$var wire 1 Y sum1 $end
$var wire 1 Z sum $end
$var wire 1 [ cout $end
$var wire 1 \ carry2 $end
$var wire 1 ] carry1 $end
$scope module HA_01 $end
$var wire 1 V a $end
$var wire 1 W b $end
$var wire 1 Y sum $end
$var wire 1 ] carry $end
$scope module AG_01 $end
$var wire 1 V a $end
$var wire 1 W b $end
$var wire 1 ] y $end
$upscope $end
$scope module XG_01 $end
$var wire 1 V a $end
$var wire 1 W b $end
$var wire 1 Y y $end
$upscope $end
$upscope $end
$scope module HA_02 $end
$var wire 1 Y a $end
$var wire 1 X b $end
$var wire 1 Z sum $end
$var wire 1 \ carry $end
$scope module AG_01 $end
$var wire 1 Y a $end
$var wire 1 X b $end
$var wire 1 \ y $end
$upscope $end
$scope module XG_01 $end
$var wire 1 Y a $end
$var wire 1 X b $end
$var wire 1 Z y $end
$upscope $end
$upscope $end
$scope module OR_01 $end
$var wire 1 ] a $end
$var wire 1 \ b $end
$var wire 1 [ y $end
$upscope $end
$upscope $end
$scope module fa4 $end
$var wire 1 ^ a $end
$var wire 1 _ b $end
$var wire 1 ` cin $end
$var wire 1 a sum1 $end
$var wire 1 b sum $end
$var wire 1 c cout $end
$var wire 1 d carry2 $end
$var wire 1 e carry1 $end
$scope module HA_01 $end
$var wire 1 ^ a $end
$var wire 1 _ b $end
$var wire 1 a sum $end
$var wire 1 e carry $end
$scope module AG_01 $end
$var wire 1 ^ a $end
$var wire 1 _ b $end
$var wire 1 e y $end
$upscope $end
$scope module XG_01 $end
$var wire 1 ^ a $end
$var wire 1 _ b $end
$var wire 1 a y $end
$upscope $end
$upscope $end
$scope module HA_02 $end
$var wire 1 a a $end
$var wire 1 ` b $end
$var wire 1 b sum $end
$var wire 1 d carry $end
$scope module AG_01 $end
$var wire 1 a a $end
$var wire 1 ` b $end
$var wire 1 d y $end
$upscope $end
$scope module XG_01 $end
$var wire 1 a a $end
$var wire 1 ` b $end
$var wire 1 b y $end
$upscope $end
$upscope $end
$scope module OR_01 $end
$var wire 1 e a $end
$var wire 1 d b $end
$var wire 1 c y $end
$upscope $end
$upscope $end
$scope module fa5 $end
$var wire 1 f a $end
$var wire 1 g b $end
$var wire 1 h cin $end
$var wire 1 i sum1 $end
$var wire 1 j sum $end
$var wire 1 k cout $end
$var wire 1 l carry2 $end
$var wire 1 m carry1 $end
$scope module HA_01 $end
$var wire 1 f a $end
$var wire 1 g b $end
$var wire 1 i sum $end
$var wire 1 m carry $end
$scope module AG_01 $end
$var wire 1 f a $end
$var wire 1 g b $end
$var wire 1 m y $end
$upscope $end
$scope module XG_01 $end
$var wire 1 f a $end
$var wire 1 g b $end
$var wire 1 i y $end
$upscope $end
$upscope $end
$scope module HA_02 $end
$var wire 1 i a $end
$var wire 1 h b $end
$var wire 1 j sum $end
$var wire 1 l carry $end
$scope module AG_01 $end
$var wire 1 i a $end
$var wire 1 h b $end
$var wire 1 l y $end
$upscope $end
$scope module XG_01 $end
$var wire 1 i a $end
$var wire 1 h b $end
$var wire 1 j y $end
$upscope $end
$upscope $end
$scope module OR_01 $end
$var wire 1 m a $end
$var wire 1 l b $end
$var wire 1 k y $end
$upscope $end
$upscope $end
$scope module fa6 $end
$var wire 1 n a $end
$var wire 1 o b $end
$var wire 1 p cin $end
$var wire 1 q sum1 $end
$var wire 1 r sum $end
$var wire 1 s cout $end
$var wire 1 t carry2 $end
$var wire 1 u carry1 $end
$scope module HA_01 $end
$var wire 1 n a $end
$var wire 1 o b $end
$var wire 1 q sum $end
$var wire 1 u carry $end
$scope module AG_01 $end
$var wire 1 n a $end
$var wire 1 o b $end
$var wire 1 u y $end
$upscope $end
$scope module XG_01 $end
$var wire 1 n a $end
$var wire 1 o b $end
$var wire 1 q y $end
$upscope $end
$upscope $end
$scope module HA_02 $end
$var wire 1 q a $end
$var wire 1 p b $end
$var wire 1 r sum $end
$var wire 1 t carry $end
$scope module AG_01 $end
$var wire 1 q a $end
$var wire 1 p b $end
$var wire 1 t y $end
$upscope $end
$scope module XG_01 $end
$var wire 1 q a $end
$var wire 1 p b $end
$var wire 1 r y $end
$upscope $end
$upscope $end
$scope module OR_01 $end
$var wire 1 u a $end
$var wire 1 t b $end
$var wire 1 s y $end
$upscope $end
$upscope $end
$scope module fa7 $end
$var wire 1 v a $end
$var wire 1 w b $end
$var wire 1 x cin $end
$var wire 1 y sum1 $end
$var wire 1 z sum $end
$var wire 1 % cout $end
$var wire 1 { carry2 $end
$var wire 1 | carry1 $end
$scope module HA_01 $end
$var wire 1 v a $end
$var wire 1 w b $end
$var wire 1 y sum $end
$var wire 1 | carry $end
$scope module AG_01 $end
$var wire 1 v a $end
$var wire 1 w b $end
$var wire 1 | y $end
$upscope $end
$scope module XG_01 $end
$var wire 1 v a $end
$var wire 1 w b $end
$var wire 1 y y $end
$upscope $end
$upscope $end
$scope module HA_02 $end
$var wire 1 y a $end
$var wire 1 x b $end
$var wire 1 z sum $end
$var wire 1 { carry $end
$scope module AG_01 $end
$var wire 1 y a $end
$var wire 1 x b $end
$var wire 1 { y $end
$upscope $end
$scope module XG_01 $end
$var wire 1 y a $end
$var wire 1 x b $end
$var wire 1 z y $end
$upscope $end
$upscope $end
$scope module OR_01 $end
$var wire 1 | a $end
$var wire 1 { b $end
$var wire 1 % y $end
$upscope $end
$upscope $end
$scope module overflow_xor $end
$var wire 1 } a $end
$var wire 1 % b $end
$var wire 1 # y $end
$upscope $end
$upscope $end
$scope task check $end
$var reg 8 ~ expected_result [7:0] $end
$var reg 1 !" expected_zero $end
$var reg 64 "" test_name [63:0] $end
$upscope $end
$upscope $end
$enddefinitions $end
$comment Show the parameter values. $end
$dumpall
$end
#0
$dumpvars
bx ""
x!"
bx ~
0}
0|
0{
0z
0y
0x
0w
0v
0u
0t
0s
0r
0q
0p
0o
0n
0m
0l
0k
0j
0i
0h
0g
0f
0e
0d
0c
1b
1a
0`
1_
0^
0]
0\
0[
1Z
1Y
0X
0W
1V
0U
0T
0S
1R
1Q
0P
1O
0N
0M
0L
0K
1J
1I
0H
0G
1F
0E
0D
0C
0B
0A
0@
0?
0>
0=
0<
0;
0:
09
18
17
06
05
14
13
02
01
00
0/
b10100 .
b0 -
b11110 ,
b10100 +
b1010 *
0)
0(
b10100 '
b1010 &
0%
0$
0#
b11110 "
0!
$end
#10000
b100010001000100001000000011000100110000001010110011001000110000 ""
0!"
b11110 ~
#15000
1!
0R
0b
0Q
0a
0O
0_
0J
b0 "
b0 ,
0Z
04
b0 .
08
0I
0Y
03
07
0F
0V
b0 '
b0 +
b0 &
b0 *
#25000
b110010101110010011011110010000001100110011011000110000101100111 ""
1!"
b0 ~
#30000
1%
1{
0#
1x
1}
1s
1t
1p
1k
1l
1h
1c
1d
1`
1[
1\
1X
1S
1T
1P
1K
1L
1H
b1111111 -
1C
1E
0$
1@
0B
0J
0R
0Z
0b
0j
0r
1!
b0 "
b0 ,
0z
b1 .
10
0A
1I
1Q
1Y
1a
1i
1q
1y
1/
1?
1F
1N
1V
1^
1f
1n
1v
b1 '
b1 +
b11111111 &
b11111111 *
#40000
b110111101110110011001010111001001100110011011000110111101110111 ""
#46000
0P
0`
1p
1x
1}
0#
0T
0R
0d
0b
0K
0[
1k
b1110101 -
1s
1%
0$
1U
0Q
1e
0a
1D
0L
1J
0\
1Z
1l
0j
1t
0r
1{
0z
1O
1_
1g
1o
1w
0E
1A
0I
0Y
1i
1q
1y
0!
b1010 "
b1010 ,
0B
14
18
1:
1<
b11110101 .
1>
0/
11
15
0?
0F
0V
0f
0n
0v
1)
1(
b1010 '
b1010 +
b10100 &
b10100 *
#56000
b101010101000010001000000011001000110000001011010011000100110000 ""
0!"
b1010 ~
#61000
1!
1%
0$
1{
0z
0#
1x
1}
1s
1T
1d
1t
0r
1P
1`
1p
1K
1X
1[
1k
1L
0J
1S
0R
1\
0Z
1l
0j
1I
0U
1Q
1Y
1h
0@
1G
0O
1W
1D
0B
b1111111 -
1c
b0 "
b0 ,
0b
00
12
04
b11111010 .
16
0E
1A
0e
1a
1/
01
13
05
1?
0^
b101 '
b101 +
b101 &
b101 *
#71000
b110010101110010011011110010000001100110011011000110000101100111 ""
1!"
b0 ~
#76000
0p
0k
1J
0P
0h
0K
0c
0L
0T
0R
0d
1b
1H
0I
1U
0Q
0a
b1001101 -
1C
1@
0G
1O
0_
0g
1D
0B
0l
1j
0t
0!
b110010 "
b110010 ,
0r
10
02
14
08
b11001101 .
0:
1A
0m
1i
1u
0q
0/
11
03
17
19
0?
1f
1n
b110010 '
b110010 +
b1100100 &
b1100100 *
#86000
b100001000100000001100010011000000110000001011010011010100110000 ""
0!"
b110010 ~
#91000
0b
0`
0X
0[
0%
0#
0S
1R
0\
0Z
0{
0x
0}
0U
1Q
0Y
0y
1D
0B
0j
b1 -
0s
b110 "
b110 ,
0r
0@
0O
0W
0o
0w
0E
1A
0i
0u
0q
00
04
06
0<
b0 .
0>
01
07
09
1?
0f
0n
0(
b0 '
b0 +
b101 &
b101 *
#101000
b100100101001110010000110010000000110101 ""
b110 ~
#106000
1%
1{
1!
0#
1x
1}
1s
1t
1p
1k
1l
1h
1c
1d
1`
1[
1\
1X
1S
1T
0R
1P
b1111111 -
1K
0$
1L
0J
0Z
0b
0j
0r
b0 "
b0 ,
0z
1I
1Y
1a
1i
1q
1y
1F
1V
1^
1f
1n
1v
b11111111 &
b11111111 *
#116000
b110000101110000011100110010000001110100011011110010000000110000 ""
1!"
b0 ~
#121000
1R
0T
1P
1`
1h
1p
1x
1}
0#
1E
0A
1U
0Q
1K
1[
1c
1k
1s
1%
0$
1H
1@
1G
1O
1W
1_
1g
1o
1w
1L
0J
1\
0Z
1d
0b
1l
0j
1t
0r
1{
0z
b1111111 -
1C
10
12
14
16
18
1:
1<
b11111111 .
1>
1I
1Y
1a
1i
1q
1y
0D
0!
b100 "
b100 ,
0B
1/
11
13
15
17
19
1;
1=
0F
0V
0^
0f
0n
0v
0)
b11111111 '
b11111111 +
b101 &
b101 *
#131000
b100010001000101010000110010000000110101 ""
0!"
b100 ~
#136000
1T
1!
b0 "
b0 ,
0R
0U
1Q
0N
b1 &
b1 *
#146000
b10000001100111011010010111011001100101011100110010000000110000 ""
1!"
b0 ~
#151000
0%
1$
0{
1z
0#
0x
0}
0s
0t
1r
0p
0k
0l
1j
0h
0c
0d
1b
0P
0`
0K
0[
0L
1J
0\
1Z
0H
0X
0C
b0 -
0S
0T
0R
0Q
0D
0@
0O
0E
0A
0!
b11111011 "
b11111011 ,
1B
00
b11111010 .
04
01
05
07
09
0;
0=
0?
1)
1(
b101 '
b101 +
b0 &
b0 *
#161000
b110111000100000001110000010110101100010011010010111010000101001 ""
0!"
b11111011 ~
#166000
b11111111 "
b11111111 ,
1R
1Q
1O
b11111110 .
14
03
b1 '
b1 +
#176000
b11111111 ~
#182000
1!
1%
0$
1{
0z
0#
1x
1}
1s
1t
0r
1p
1k
1L
1\
1l
0j
1H
1X
1h
1C
1S
1c
1D
0B
1T
0R
1d
0b
1A
1P
1`
1@
0G
0W
1K
0J
b1111111 -
1[
b0 "
b0 ,
0Z
10
02
b11110101 .
06
0M
1I
0]
1Y
0/
11
15
1F
1V
b1010 '
b1010 +
b1010 &
b1010 *
#193000
0H
0X
0C
b1111010 -
0S
0D
1B
0L
0J
0T
1R
0\
0!
b101 "
b101 ,
0Z
0A
1M
0I
0Q
1]
0Y
0@
1G
0O
1W
00
12
04
b11111010 .
16
1/
01
13
05
b101 '
b101 +
#204000
0%
1$
0{
1z
0#
0x
0}
0s
0t
1r
0p
0k
0l
1j
0h
0c
1H
1X
0d
1b
1E
1U
1C
0P
1S
0`
1@
0G
1O
0W
0D
1B
0K
1J
0T
0R
b101 -
0[
b11111011 "
b11111011 ,
1Z
10
02
14
b11110101 .
06
0A
0M
0I
0Q
0]
0Y
0/
11
03
15
1?
0F
1N
0V
b1010 '
b1010 +
b101 &
b101 *
#215000
0$
0b
0j
0r
0z
0a
0i
0q
0y
0_
0g
0o
0w
b1010 "
b1010 ,
0B
08
0:
0<
b101 .
0>
1/
01
13
05
0)
0(
b101 '
b101 +
#225000
b11001000100000001101010111100000110010001111010011000100110000 ""
b1010 ~
#230000
1$
1z
1#
1x
1}
0!
1s
0J
0Z
1u
0H
0X
0@
0O
1o
0C
0B
b1000000 -
0S
0R
b10000000 "
b10000000 ,
0r
00
04
b1000000 .
1<
0E
0A
0U
0Q
0q
0/
03
1;
0?
0N
1n
b1000000 '
b1000000 +
b1000000 &
b1000000 *
#240000
b11011000110100011110000011001000111101001100010011001000111000 ""
b10000000 ~
#245000
1b
1`
b1001000 -
1[
0#
1]
1|
1%
1$
1W
1w
0Z
0{
0!
b10010000 "
b10010000 ,
1z
16
b11001000 .
1>
0Y
0y
15
1=
1V
1v
b11001000 '
b11001000 +
b11001000 &
b11001000 *
#256000
1\
1X
1S
1T
1b
1P
1`
0%
1B
1K
0R
1[
0Z
0#
1A
1M
1Q
0]
1Y
0x
0}
0$
1@
1G
1O
0W
0o
0w
0J
b1110 -
0s
0r
0{
b10001 "
b10001 ,
0z
10
12
14
06
0<
b111 .
0>
0I
0u
0q
0|
0y
1/
11
13
05
0;
0=
1F
0n
0v
b111 '
b111 +
b1010 &
b1010 *
#266000
b100111001010011010101000010000000110001001100000010101100110111 ""
b10001 ~
#271000
1%
1{
0#
1x
1}
1s
1t
1p
1k
1l
0$
1`
1h
0j
0r
0z
0P
1[
1c
0H
0A
1e
1i
1q
1y
0K
0J
0T
0R
1\
0Z
0d
0!
1b
b1111100 -
0C
0@
0G
1W
1_
1g
1o
1w
0M
0I
1U
0Q
1Y
0a
0D
b10001 "
b10001 ,
1B
00
02
16
18
1:
1<
b11111100 .
1>
03
0F
1N
0V
1^
1)
1(
b11 '
b11 +
b10100 &
b10100 *
#281000
b100111001010011010101000010000000110010001100000010110100110011 ""
